{
"kwic": [
{
"corpus": "DA",
"match": {
"position": 290736,
"start": 16,
"end": 19
},
"structs": {
"text_date": "2010-05-03 22:49:51",
"text_id": "coverage-akad-jamlikhet-vantar",
"text_author": "Bj\u00f6rn Elmbrant"
},
"tokens": [
{
"word": "Klyftorna",
"deprel": "SS",
"dephead": "2",
"ref": "1",
"lemma": "|klyfta|",
"msd": "NN.UTR.PLU.DEF.NOM",
"pos": "NN"
},
{
"word": "ska",
"deprel": "ROOT",
"dephead": null,
"ref": "2",
"lemma": "|skola|",
"msd": "VB.PRS.AKT",
"pos": "VB"
},
{
"word": "inte",
"deprel": "NA",
"dephead": "2",
"ref": "3",
"lemma": "|inte|",
"msd": "AB",
"pos": "AB"
},
{
"word": "\u00f6ka",
"deprel": "VG",
"dephead": "2",
"ref": "4",
"lemma": "|\u00f6ka|",
"msd": "VB.INF.AKT",
"pos": "VB"
},
{
"word": "ytterligare",
"deprel": "AA",
"dephead": "4",
"ref": "5",
"lemma": "|ytterlig|",
"msd": "AB.KOM",
"pos": "AB"
},
{
"word": ",",
"deprel": "IK",
"dephead": "2",
"ref": "6",
"lemma": "|",
"msd": "MID",
"pos": "MID"
},
{
"word": "det",
"deprel": "SS",
"dephead": "8",
"ref": "7",
"lemma": "|den|",
"msd": "PN.NEU.SIN.DEF.SUB+OBJ",
"pos": "PN"
},
{
"word": "\u00e4r",
"deprel": "MS",
"dephead": "2",
"ref": "8",
"lemma": "|vara|",
"msd": "VB.PRS.AKT",
"pos": "VB"
},
{
"word": "ett",
"deprel": "DT",
"dephead": "10",
"ref": "9",
"lemma": "|en|",
"msd": "DT.NEU.SIN.IND",
"pos": "DT"
},
{
"word": "besked",
"deprel": "SP",
"dephead": "8",
"ref": "10",
"lemma": "|besked|",
"msd": "NN.NEU.SIN.IND.NOM",
"pos": "NN"
},
{
"word": "fr\u00e5n",
"deprel": "OA",
"dephead": "8",
"ref": "11",
"lemma": "|fr\u00e5n|",
"msd": "PP",
"pos": "PP"
},
{
"word": "de",
"deprel": "DT",
"dephead": "13",
"ref": "12",
"lemma": "|en|",
"msd": "DT.UTR+NEU.PLU.DEF",
"pos": "DT"
},
{
"word": "r\u00f6dgr\u00f6na",
"deprel": "PA",
"dephead": "11",
"ref": "13",
"lemma": "|r\u00f6dgr\u00f6n|",
"msd": "JJ.POS.UTR+NEU.PLU.IND+DEF.NOM",
"pos": "JJ"
},
{
"word": ",",
"deprel": "IK",
"dephead": "8",
"ref": "14",
"lemma": "|",
"msd": "MID",
"pos": "MID"
},
{
"word": "n\u00e5got",
"deprel": "CJ",
"dephead": "14",
"ref": "15",
"lemma": "|n\u00e5gon|",
"msd": "PN.NEU.SIN.IND.SUB+OBJ",
"pos": "PN"
},
{
"word": "som",
"deprel": "SS",
"dephead": "17",
"ref": "16",
"lemma": "|",
"msd": "HP.-.-.-",
"pos": "HP"
},
{
"word": "kommer",
"deprel": "ET",
"dephead": "15",
"ref": "17",
"lemma": "|komma|",
"msd": "VB.PRS.AKT",
"pos": "VB"
},
{
"word": "att",
"deprel": "VG",
"dephead": "17",
"ref": "18",
"lemma": "|att|",
"msd": "IE",
"pos": "IE"
},
{
"word": "kr\u00e4va",
"deprel": "IF",
"dephead": "18",
"ref": "19",
"lemma": "|kr\u00e4va|",
"msd": "VB.INF.AKT",
"pos": "VB"
},
{
"word": "ytterligare",
"deprel": "DT",
"dephead": "21",
"ref": "20",
"lemma": "|ytterlig|",
"msd": "JJ.KOM.UTR+NEU.SIN+PLU.IND+DEF.NOM",
"pos": "JJ"
},
{
"word": "uppoffringar",
"deprel": "OO",
"dephead": "19",
"ref": "21",
"lemma": "|uppoffring|",
"msd": "NN.UTR.PLU.IND.NOM",
"pos": "NN"
},
{
"word": "fram\u00f6ver",
"deprel": "TA",
"dephead": "19",
"ref": "22",
"lemma": "|fram\u00f6ver|",
"msd": "AB",
"pos": "AB"
},
{
"word": ".",
"deprel": "IP",
"dephead": "2",
"ref": "23",
"lemma": "|",
"msd": "MAD",
"pos": "MAD"
}
]
},
{
"corpus": "DA",
"match": {
"position": 295894,
"start": 8,
"end": 10
},
"structs": {
"text_date": "2010-05-26 12:50:55",
"text_id": "7029",
"text_author": "Mikael F\u00e4rnbo"
},
"tokens": [
{
"word": "Att",
"deprel": "SS",
"dephead": "17",
"ref": "1",
"lemma": "|att|",
"msd": "SN",
"pos": "SN"
},
{
"word": "tj\u00e4nstem\u00e4nnen",
"deprel": "SS",
"dephead": "3",
"ref": "2",
"lemma": "|tj\u00e4nsteman|",
"msd": "NN.UTR.PLU.DEF.NOM",
"pos": "NN"
},
{
"word": "gick",
"deprel": "UA",
"dephead": "1",
"ref": "3",
"lemma": "|g\u00e5|",
"msd": "VB.PRT.AKT",
"pos": "VB"
},
{
"word": "f\u00f6rst",
"deprel": "TA",
"dephead": "3",
"ref": "4",
"lemma": "|f\u00f6rst|",
"msd": "AB",
"pos": "AB"
},
{
"word": "\u00e4r",
"deprel": "MS",
"dephead": "8",
"ref": "5",
"lemma": "|vara|",
"msd": "VB.PRS.AKT",
"pos": "VB"
},
{
"word": "ett",
"deprel": "DT",
"dephead": "7",
"ref": "6",
"lemma": "|en|",
"msd": "DT.NEU.SIN.IND",
"pos": "DT"
},
{
"word": "trendbrott",
"deprel": "SP",
"dephead": "5",
"ref": "7",
"lemma": "|trendbrott|",
"msd": "NN.NEU.SIN.IND.NOM",
"pos": "NN"
},
{
"word": "och",
"deprel": "UA",
"dephead": "1",
"ref": "8",
"lemma": "|och|",
"msd": "KN",
"pos": "KN"
},
{
"word": "kommer",
"deprel": "+F",
"dephead": "8",
"ref": "9",
"lemma": "|komma|",
"msd": "VB.PRS.AKT",
"pos": "VB"
},
{
"word": "f\u00e5",
"deprel": "VG",
"dephead": "9",
"ref": "10",
"lemma": "|f\u00e5|",
"msd": "VB.INF.AKT",
"pos": "VB"
},
{
"word": "mycket",
"deprel": "AA",
"dephead": "12",
"ref": "11",
"lemma": "|mycket|",
"msd": "AB.POS",
"pos": "AB"
},
{
"word": "stor",
"deprel": "AT",
"dephead": "13",
"ref": "12",
"lemma": "|stor|",
"msd": "JJ.POS.UTR.SIN.IND.NOM",
"pos": "JJ"
},
{
"word": "betydelse",
"deprel": "OO",
"dephead": "10",
"ref": "13",
"lemma": "|betydelse|",
"msd": "NN.UTR.SIN.IND.NOM",
"pos": "NN"
},
{
"word": "f\u00f6r",
"deprel": "OA",
"dephead": "10",
"ref": "14",
"lemma": "|f\u00f6r|",
"msd": "PP",
"pos": "PP"
},
{
"word": "framtidens",
"deprel": "DT",
"dephead": "16",
"ref": "15",
"lemma": "|framtid|",
"msd": "NN.UTR.SIN.DEF.GEN",
"pos": "NN"
},
{
"word": "l\u00f6nebildning",
"deprel": "PA",
"dephead": "14",
"ref": "16",
"lemma": "|l\u00f6nebildning|",
"msd": "NN.UTR.SIN.IND.NOM",
"pos": "NN"
},
{
"word": ".",
"deprel": "ROOT",
"dephead": null,
"ref": "17",
"lemma": "|",
"msd": "MAD",
"pos": "MAD"
}
]
},
{
"corpus": "DA",
"match": {
"position": 302645,
"start": 5,
"end": 8
},
"structs": {
"text_date": "2010-05-26 12:50:55",
"text_id": "7029",
"text_author": "Mikael F\u00e4rnbo"
},
"tokens": [
{
"word": "S\u00e5",
"deprel": "AA",
"dephead": "6",
"ref": "1",
"lemma": "|s\u00e5|",
"msd": "AB",
"pos": "AB"
},
{
"word": "av",
"deprel": "KA",
"dephead": "1",
"ref": "2",
"lemma": "|av|av_allt_att_d\u00f6ma|",
"msd": "PP",
"pos": "PP"
},
{
"word": "allt",
"deprel": "HD",
"dephead": "1",
"ref": "3",
"lemma": "|all|av_allt_att_d\u00f6ma:2|",
"msd": "PN.NEU.SIN.IND.SUB+OBJ",
"pos": "PN"
},
{
"word": "att",
"deprel": "UA",
"dephead": "1",
"ref": "4",
"lemma": "|att|av_allt_att_d\u00f6ma:2|",
"msd": "IE",
"pos": "IE"
},
{
"word": "d\u00f6ma",
"deprel": "IF",
"dephead": "4",
"ref": "5",
"lemma": "|d\u00f6ma|av_allt_att_d\u00f6ma:2|",
"msd": "VB.INF.AKT",
"pos": "VB"
},
{
"word": "kommer",
"deprel": "ROOT",
"dephead": null,
"ref": "6",
"lemma": "|komma|",
"msd": "VB.PRS.AKT",
"pos": "VB"
},
{
"word": "tj\u00e4nstemannaf\u00f6rbunden",
"deprel": "SS",
"dephead": "6",
"ref": "7",
"lemma": "|tj\u00e4nstemannaf\u00f6rbund|",
"msd": "NN.NEU.PLU.DEF.NOM",
"pos": "NN"
},
{
"word": "s\u00e4tta",
"deprel": "VG",
"dephead": "6",
"ref": "8",
"lemma": "|s\u00e4tta|",
"msd": "VB.INF.AKT",
"pos": "VB"
},
{
"word": "m\u00e4rket",
"deprel": "OO",
"dephead": "8",
"ref": "9",
"lemma": "|m\u00e4rke|",
"msd": "NN.NEU.SIN.DEF.NOM",
"pos": "NN"
},
{
"word": "\u00e4ven",
"deprel": "+A",
"dephead": "11",
"ref": "10",
"lemma": "|\u00e4ven|",
"msd": "AB",
"pos": "AB"
},
{
"word": "inf\u00f6r",
"deprel": "RA",
"dephead": "8",
"ref": "11",
"lemma": "|inf\u00f6r|",
"msd": "PP",
"pos": "PP"
},
{
"word": "n\u00e4sta",
"deprel": "DT",
"dephead": "13",
"ref": "12",
"lemma": "|n\u00e4sta|",
"msd": "JJ.POS.UTR+NEU.SIN+PLU.IND+DEF.NOM",
"pos": "JJ"
},
{
"word": "avtalsr\u00f6relse",
"deprel": "PA",
"dephead": "11",
"ref": "13",
"lemma": "|avtalsr\u00f6relse|",
"msd": "NN.UTR.SIN.IND.NOM",
"pos": "NN"
},
{
"word": ".",
"deprel": "IP",
"dephead": "6",
"ref": "14",
"lemma": "|",
"msd": "MAD",
"pos": "MAD"
}
]
},
{
"corpus": "DA",
"match": {
"position": 304508,
"start": 20,
"end": 22
},
"structs": {
"text_date": "2010-05-31 11:26:10",
"text_id": "7115",
"text_author": "Yonna Waltersson"
},
"tokens": [
{
"word": "Men",
"deprel": "ROOT",
"dephead": null,
"ref": "1",
"lemma": "|men|",
"msd": "KN",
"pos": "KN"
},
{
"word": "\u00e4nda",
"deprel": "AA",
"dephead": "3",
"ref": "2",
"lemma": "|\u00e4nda|",
"msd": "AB",
"pos": "AB"
},
{
"word": "fram",
"deprel": "TA",
"dephead": "6",
"ref": "3",
"lemma": "|fram|",
"msd": "AB",
"pos": "AB"
},
{
"word": "till",
"deprel": "TA",
"dephead": "3",
"ref": "4",
"lemma": "|till|",
"msd": "PP",
"pos": "PP"
},
{
"word": "april",
"deprel": "PA",
"dephead": "4",
"ref": "5",
"lemma": "|april|",
"msd": "NN.UTR.SIN.IND.NOM",
"pos": "NN"
},
{
"word": "kunde",
"deprel": "MS",
"dephead": "1",
"ref": "6",
"lemma": "|kunna|",
"msd": "VB.PRT.AKT",
"pos": "VB"
},
{
"word": "landstingen",
"deprel": "SS",
"dephead": "6",
"ref": "7",
"lemma": "|landsting|",
"msd": "NN.NEU.PLU.DEF.NOM",
"pos": "NN"
},
{
"word": "forts\u00e4tta",
"deprel": "VG",
"dephead": "6",
"ref": "8",
"lemma": "|forts\u00e4tta|",
"msd": "VB.INF.AKT",
"pos": "VB"
},
{
"word": "placera",
"deprel": "OO",
"dephead": "8",
"ref": "9",
"lemma": "|placera|",
"msd": "VB.INF.AKT",
"pos": "VB"
},
{
"word": "patienterna",
"deprel": "OO",
"dephead": "9",
"ref": "10",
"lemma": "|patient|",
"msd": "NN.UTR.PLU.DEF.NOM",
"pos": "NN"
},
{
"word": "i",
"deprel": "RA",
"dephead": "9",
"ref": "11",
"lemma": "|i|",
"msd": "PP",
"pos": "PP"
},
{
"word": "de",
"deprel": "DT",
"dephead": "14",
"ref": "12",
"lemma": "|en|",
"msd": "DT.UTR+NEU.PLU.DEF",
"pos": "DT"
},
{
"word": "tv\u00e5",
"deprel": "DT",
"dephead": "14",
"ref": "13",
"lemma": "|tv\u00e5|",
"msd": "RG.NOM",
"pos": "RG"
},
{
"word": "k\u00f6erna",
"deprel": "PA",
"dephead": "11",
"ref": "14",
"lemma": "|k\u00f6|",
"msd": "NN.UTR.PLU.DEF.NOM",
"pos": "NN"
},
{
"word": "och",
"deprel": "PA",
"dephead": "11",
"ref": "15",
"lemma": "|och|",
"msd": "KN",
"pos": "KN"
},
{
"word": "G\u00f6ran",
"deprel": "CJ",
"dephead": "15",
"ref": "16",
"lemma": "|G\u00f6ran|",
"msd": "PM.NOM",
"pos": "PM"
},
{
"word": "H\u00e4gglund",
"deprel": "HD",
"dephead": "16",
"ref": "17",
"lemma": "|H\u00e4gglund|",
"msd": "PM.NOM",
"pos": "PM"
},
{
"word": "s\u00e4ger",
"deprel": "ET",
"dephead": "15",
"ref": "18",
"lemma": "|s\u00e4ga|",
"msd": "VB.PRS.AKT",
"pos": "VB"
},
{
"word": "att",
"deprel": "OO",
"dephead": "18",
"ref": "19",
"lemma": "|att|",
"msd": "SN",
"pos": "SN"
},
{
"word": "det",
"deprel": "SS",
"dephead": "21",
"ref": "20",
"lemma": "|den|",
"msd": "PN.NEU.SIN.DEF.SUB+OBJ",
"pos": "PN"
},
{
"word": "kommer",
"deprel": "UA",
"dephead": "19",
"ref": "21",
"lemma": "|komma|",
"msd": "VB.PRS.AKT",
"pos": "VB"
},
{
"word": "ta",
"deprel": "VG",
"dephead": "21",
"ref": "22",
"lemma": "|ta|",
"msd": "VB.INF.AKT",
"pos": "VB"
},
{
"word": "ytterligare",
"deprel": "DT",
"dephead": "24",
"ref": "23",
"lemma": "|ytterlig|",
"msd": "JJ.KOM.UTR+NEU.SIN+PLU.IND+DEF.NOM",
"pos": "JJ"
},
{
"word": "m\u00e5nader",
"deprel": "OO",
"dephead": "22",
"ref": "24",
"lemma": "|m\u00e5nad|",
"msd": "NN.UTR.PLU.IND.NOM",
"pos": "NN"
},
{
"word": "innan",
"deprel": "TA",
"dephead": "22",
"ref": "25",
"lemma": "|innan|",
"msd": "SN",
"pos": "SN"
},
{
"word": "landstingen",
"deprel": "SS",
"dephead": "28",
"ref": "26",
"lemma": "|landsting|",
"msd": "NN.NEU.PLU.DEF.NOM",
"pos": "NN"
},
{
"word": "halt",
"deprel": "AA",
"dephead": "28",
"ref": "27",
"lemma": "|hal|halt|",
"msd": "AB.POS",
"pos": "AB"
},
{
"word": "f\u00e5tt",
"deprel": "UA",
"dephead": "25",
"ref": "28",
"lemma": "|f\u00e5|",
"msd": "VB.SUP.AKT",
"pos": "VB"
},
{
"word": "ordning",
"deprel": "OO",
"dephead": "28",
"ref": "29",
"lemma": "|ordning|",
"msd": "NN.UTR.SIN.IND.NOM",
"pos": "NN"
},
{
"word": "p\u00e5",
"deprel": "RA",
"dephead": "28",
"ref": "30",
"lemma": "|p\u00e5|",
"msd": "PP",
"pos": "PP"
},
{
"word": "statistiken",
"deprel": "PA",
"dephead": "30",
"ref": "31",
"lemma": "|statistik|",
"msd": "NN.UTR.SIN.DEF.NOM",
"pos": "NN"
},
{
"word": ".",
"deprel": "IP",
"dephead": "6",
"ref": "32",
"lemma": "|",
"msd": "MAD",
"pos": "MAD"
}
]
},
{
"corpus": "DA",
"match": {
"position": 304524,
"start": 4,
"end": 8
},
"structs": {
"text_date": "2010-05-31 11:26:10",
"text_id": "7115",
"text_author": "Yonna Waltersson"
},
"tokens": [
{
"word": "Uppemot",
"deprel": "AA",
"dephead": "5",
"ref": "1",
"lemma": "|",
"msd": "PP",
"pos": "PP"
},
{
"word": "vart",
"deprel": "DT",
"dephead": "4",
"ref": "2",
"lemma": "|var|",
"msd": "DT.NEU.SIN.IND",
"pos": "DT"
},
{
"word": "fj\u00e4rde",
"deprel": "DT",
"dephead": "4",
"ref": "3",
"lemma": "|fyra|",
"msd": "RO.NOM",
"pos": "RO"
},
{
"word": "landsting",
"deprel": "PA",
"dephead": "1",
"ref": "4",
"lemma": "|landsting|",
"msd": "NN.NEU.SIN.IND.NOM",
"pos": "NN"
},
{
"word": "kommer",
"deprel": "ROOT",
"dephead": null,
"ref": "5",
"lemma": "|komma|",
"msd": "VB.PRS.AKT",
"pos": "VB"
},
{
"word": "inte",
"deprel": "NA",
"dephead": "5",
"ref": "6",
"lemma": "|inte|",
"msd": "AB",
"pos": "AB"
},
{
"word": "att",
"deprel": "VG",
"dephead": "5",
"ref": "7",
"lemma": "|att|",
"msd": "IE",
"pos": "IE"
},
{
"word": "kunna",
"deprel": "IF",
"dephead": "7",
"ref": "8",
"lemma": "|kunna|",
"msd": "VB.INF.AKT",
"pos": "VB"
},
{
"word": "redovisa",
"deprel": "VG",
"dephead": "8",
"ref": "9",
"lemma": "|redovisa|",
"msd": "VB.INF.AKT",
"pos": "VB"
},
{
"word": "k\u00f6tiderna",
"deprel": "OO",
"dephead": "9",
"ref": "10",
"lemma": "|k\u00f6tid|",
"msd": "NN.UTR.PLU.DEF.NOM",
"pos": "NN"
},
{
"word": "enligt",
"deprel": "AA",
"dephead": "9",
"ref": "11",
"lemma": "|enligt|",
"msd": "PP",
"pos": "PP"
},
{
"word": "de",
"deprel": "DT",
"dephead": "14",
"ref": "12",
"lemma": "|en|",
"msd": "DT.UTR+NEU.PLU.DEF",
"pos": "DT"
},
{
"word": "nya",
"deprel": "AT",
"dephead": "14",
"ref": "13",
"lemma": "|ny|",
"msd": "JJ.POS.UTR+NEU.PLU.IND+DEF.NOM",
"pos": "JJ"
},
{
"word": "kriterierna",
"deprel": "PA",
"dephead": "11",
"ref": "14",
"lemma": "|kriterium|",
"msd": "NN.NEU.PLU.DEF.NOM",
"pos": "NN"
},
{
"word": ".",
"deprel": "IP",
"dephead": "5",
"ref": "15",
"lemma": "|",
"msd": "MAD",
"pos": "MAD"
}
]
},
{
"corpus": "DA",
"match": {
"position": 306597,
"start": 7,
"end": 13
},
"structs": {
"text_date": "2010-05-31 11:26:10",
"text_id": "7115",
"text_author": "Yonna Waltersson"
},
"tokens": [
{
"word": "K\u00f6miljarden",
"deprel": "SS",
"dephead": "2",
"ref": "1",
"lemma": "|k\u00f6miljard|",
"msd": "NN.UTR.SIN.DEF.NOM",
"pos": "NN"
},
{
"word": "f\u00f6rblir",
"deprel": "MS",
"dephead": "6",
"ref": "2",
"lemma": "|f\u00f6rbli|",
"msd": "VB.PRS.AKT",
"pos": "VB"
},
{
"word": "en",
"deprel": "DT",
"dephead": "4",
"ref": "3",
"lemma": "|en|",
"msd": "DT.UTR.SIN.IND",
"pos": "DT"
},
{
"word": "flopp",
"deprel": "SP",
"dephead": "2",
"ref": "4",
"lemma": "|flopp|",
"msd": "NN.UTR.SIN.IND.NOM",
"pos": "NN"
},
{
"word": "\u2013",
"deprel": "IK",
"dephead": "6",
"ref": "5",
"lemma": "|",
"msd": "MID",
"pos": "MID"
},
{
"word": "men",
"deprel": "ROOT",
"dephead": null,
"ref": "6",
"lemma": "|men|",
"msd": "KN",
"pos": "KN"
},
{
"word": "det",
"deprel": "SP",
"dephead": "13",
"ref": "7",
"lemma": "|den|",
"msd": "PN.NEU.SIN.DEF.SUB+OBJ",
"pos": "PN"
},
{
"word": "kommer",
"deprel": "MS",
"dephead": "6",
"ref": "8",
"lemma": "|komma|",
"msd": "VB.PRS.AKT",
"pos": "VB"
},
{
"word": "f\u00f6rst\u00e5s",
"deprel": "MA",
"dephead": "8",
"ref": "9",
"lemma": "|f\u00f6rst\u00e5s|",
"msd": "AB",
"pos": "AB"
},
{
"word": "H\u00e4gglund",
"deprel": "SS",
"dephead": "8",
"ref": "10",
"lemma": "|H\u00e4gglund|",
"msd": "PM.NOM",
"pos": "PM"
},
{
"word": "aldrig",
"deprel": "TA",
"dephead": "8",
"ref": "11",
"lemma": "|aldrig|",
"msd": "AB",
"pos": "AB"
},
{
"word": "att",
"deprel": "VG",
"dephead": "8",
"ref": "12",
"lemma": "|att|",
"msd": "IE",
"pos": "IE"
},
{
"word": "medge",
"deprel": "IF",
"dephead": "12",
"ref": "13",
"lemma": "|medge|",
"msd": "VB.INF.AKT",
"pos": "VB"
},
{
"word": ".",
"deprel": "IP",
"dephead": "6",
"ref": "14",
"lemma": "|",
"msd": "MAD",
"pos": "MAD"
}
]
},
{
"corpus": "DA",
"match": {
"position": 309089,
"start": 1,
"end": 6
},
"structs": {
"text_date": "2010-05-10 19:49:31",
"text_id": "coverage-uppskov-men-sedan",
"text_author": "Bj\u00f6rn Elmbrant"
},
"tokens": [
{
"word": "Spekulanterna",
"deprel": "SS",
"dephead": "2",
"ref": "1",
"lemma": "|spekulant|",
"msd": "NN.UTR.PLU.DEF.NOM",
"pos": "NN"
},
{
"word": "kommer",
"deprel": "ROOT",
"dephead": null,
"ref": "2",
"lemma": "|komma|",
"msd": "VB.PRS.AKT",
"pos": "VB"
},
{
"word": "d\u00e4rf\u00f6r",
"deprel": "AA",
"dephead": "2",
"ref": "3",
"lemma": "|d\u00e4rf\u00f6r|",
"msd": "AB",
"pos": "AB"
},
{
"word": "bara",
"deprel": "CA",
"dephead": "2",
"ref": "4",
"lemma": "|bara|",
"msd": "AB",
"pos": "AB"
},
{
"word": "att",
"deprel": "VG",
"dephead": "2",
"ref": "5",
"lemma": "|att|",
"msd": "IE",
"pos": "IE"
},
{
"word": "ta",
"deprel": "IF",
"dephead": "5",
"ref": "6",
"lemma": "|ta|",
"msd": "VB.INF.AKT",
"pos": "VB"
},
{
"word": "en",
"deprel": "DT",
"dephead": "9",
"ref": "7",
"lemma": "|en|",
"msd": "DT.UTR.SIN.IND",
"pos": "DT"
},
{
"word": "tillf\u00e4llig",
"deprel": "AT",
"dephead": "9",
"ref": "8",
"lemma": "|tillf\u00e4llig|",
"msd": "JJ.POS.UTR.SIN.IND.NOM",
"pos": "JJ"
},
{
"word": "paus",
"deprel": "OO",
"dephead": "6",
"ref": "9",
"lemma": "|paus|",
"msd": "NN.UTR.SIN.IND.NOM",
"pos": "NN"
},
{
"word": ",",
"deprel": "IK",
"dephead": "6",
"ref": "10",
"lemma": "|",
"msd": "MID",
"pos": "MID"
},
{
"word": "innan",
"deprel": "TA",
"dephead": "6",
"ref": "11",
"lemma": "|innan|",
"msd": "SN",
"pos": "SN"
},
{
"word": "n\u00e4sta",
"deprel": "DT",
"dephead": "13",
"ref": "12",
"lemma": "|n\u00e4sta|",
"msd": "JJ.POS.UTR+NEU.SIN+PLU.IND+DEF.NOM",
"pos": "JJ"
},
{
"word": "offer",
"deprel": "SS",
"dephead": "14",
"ref": "13",
"lemma": "|offer|",
"msd": "NN.NEU.SIN.IND.NOM",
"pos": "NN"
},
{
"word": "utsetts",
"deprel": "UA",
"dephead": "11",
"ref": "14",
"lemma": "|utse|",
"msd": "VB.SUP.SFO",
"pos": "VB"
},
{
"word": ".",
"deprel": "IP",
"dephead": "2",
"ref": "15",
"lemma": "|",
"msd": "MAD",
"pos": "MAD"
}
]
},
{
"corpus": "DA",
"match": {
"position": 317542,
"start": 3,
"end": 6
},
"structs": {
"text_date": "2010-05-12 10:34:00",
"text_id": "ledare-det-drar-ihop-sig",
"text_author": "Nisha Besara"
},
"tokens": [
{
"word": "Nya",
"deprel": "AT",
"dephead": "2",
"ref": "1",
"lemma": "|ny|",
"msd": "JJ.POS.UTR+NEU.SIN.DEF.NOM",
"pos": "JJ"
},
{
"word": "Dagens",
"deprel": "DT",
"dephead": "3",
"ref": "2",
"lemma": "|dag|",
"msd": "NN.UTR.SIN.DEF.GEN",
"pos": "NN"
},
{
"word": "Arena",
"deprel": "SS",
"dephead": "4",
"ref": "3",
"lemma": "|",
"msd": "PM.NOM",
"pos": "PM"
},
{
"word": "kommer",
"deprel": "ROOT",
"dephead": null,
"ref": "4",
"lemma": "|komma|",
"msd": "VB.PRS.AKT",
"pos": "VB"
},
{
"word": "att",
"deprel": "VG",
"dephead": "4",
"ref": "5",
"lemma": "|att|",
"msd": "IE",
"pos": "IE"
},
{
"word": "vila",
"deprel": "IF",
"dephead": "5",
"ref": "6",
"lemma": "|vila|",
"msd": "VB.INF.AKT",
"pos": "VB"
},
{
"word": "p\u00e5",
"deprel": "OA",
"dephead": "6",
"ref": "7",
"lemma": "|p\u00e5|",
"msd": "PP",
"pos": "PP"
},
{
"word": "tre",
"deprel": "DT",
"dephead": "9",
"ref": "8",
"lemma": "|tre|",
"msd": "RG.NOM",
"pos": "RG"
},
{
"word": "ben",
"deprel": "PA",
"dephead": "7",
"ref": "9",
"lemma": "|ben|",
"msd": "NN.NEU.PLU.IND.NOM",
"pos": "NN"
},
{
"word": ":",
"deprel": "IQ",
"dephead": "9",
"ref": "10",
"lemma": "|",
"msd": "MID",
"pos": "MID"
},
{
"word": "opinion",
"deprel": "CJ",
"dephead": "14",
"ref": "11",
"lemma": "|opinion|",
"msd": "NN.UTR.SIN.IND.NOM",
"pos": "NN"
},
{
"word": ",",
"deprel": "IK",
"dephead": "14",
"ref": "12",
"lemma": "|",
"msd": "MID",
"pos": "MID"
},
{
"word": "nyheter",
"deprel": "CJ",
"dephead": "14",
"ref": "13",
"lemma": "|nyhet|",
"msd": "NN.UTR.PLU.IND.NOM",
"pos": "NN"
},
{
"word": ",",
"deprel": "AN",
"dephead": "9",
"ref": "14",
"lemma": "|",
"msd": "MID",
"pos": "MID"
},
{
"word": "f\u00f6rdjupning",
"deprel": "CJ",
"dephead": "14",
"ref": "15",
"lemma": "|f\u00f6rdjupning|",
"msd": "NN.UTR.SIN.IND.NOM",
"pos": "NN"
},
{
"word": ".",
"deprel": "IP",
"dephead": "4",
"ref": "16",
"lemma": "|",
"msd": "MAD",
"pos": "MAD"
}
]
},
{
"corpus": "DA",
"match": {
"position": 322412,
"start": 11,
"end": 14
},
"structs": {
"text_date": "2010-05-05 16:38:12",
"text_id": "editorial-dyr-affar-for-stockholmarna",
"text_author": "Yonna Waltersson"
},
"tokens": [
{
"word": "Som",
"deprel": "ROOT",
"dephead": null,
"ref": "1",
"lemma": "|",
"msd": "KN",
"pos": "KN"
},
{
"word": "att",
"deprel": "UA",
"dephead": "1",
"ref": "2",
"lemma": "|att|",
"msd": "SN",
"pos": "SN"
},
{
"word": "de",
"deprel": "DT",
"dephead": "5",
"ref": "3",
"lemma": "|en|",
"msd": "DT.UTR+NEU.PLU.DEF",
"pos": "DT"
},
{
"word": "privata",
"deprel": "AT",
"dephead": "5",
"ref": "4",
"lemma": "|privat|",
"msd": "JJ.POS.UTR+NEU.PLU.IND+DEF.NOM",
"pos": "JJ"
},
{
"word": "intressen",
"deprel": "SS",
"dephead": "12",
"ref": "5",
"lemma": "|intresse|",
"msd": "NN.NEU.PLU.IND.NOM",
"pos": "NN"
},
{
"word": "som",
"deprel": "SS",
"dephead": "7",
"ref": "6",
"lemma": "|",
"msd": "HP.-.-.-",
"pos": "HP"
},
{
"word": "skjuter",
"deprel": "ET",
"dephead": "5",
"ref": "7",
"lemma": "|skjuta|",
"msd": "VB.PRS.AKT",
"pos": "VB"
},
{
"word": "till",
"deprel": "OA",
"dephead": "7",
"ref": "8",
"lemma": "|till|",
"msd": "PP",
"pos": "PP"
},
{
"word": "1,3",
"deprel": "DT",
"dephead": "10",
"ref": "9",
"lemma": "|",
"msd": "RG.NOM",
"pos": "RG"
},
{
"word": "miljarder",
"deprel": "DT",
"dephead": "11",
"ref": "10",
"lemma": "|miljard|",
"msd": "NN.UTR.PLU.IND.NOM",
"pos": "NN"
},
{
"word": "kronor",
"deprel": "PA",
"dephead": "8",
"ref": "11",
"lemma": "|krona|",
"msd": "NN.UTR.PLU.IND.NOM",
"pos": "NN"
},
{
"word": "kommer",
"deprel": "UA",
"dephead": "2",
"ref": "12",
"lemma": "|komma|",
"msd": "VB.PRS.AKT",
"pos": "VB"
},
{
"word": "att",
"deprel": "VG",
"dephead": "12",
"ref": "13",
"lemma": "|att|",
"msd": "IE",
"pos": "IE"
},
{
"word": "f\u00e5",
"deprel": "IF",
"dephead": "13",
"ref": "14",
"lemma": "|f\u00e5|",
"msd": "VB.INF.AKT",
"pos": "VB"
},
{
"word": "en",
"deprel": "DT",
"dephead": "16",
"ref": "15",
"lemma": "|en|",
"msd": "DT.UTR.SIN.IND",
"pos": "DT"
},
{
"word": "r\u00e4nta",
"deprel": "OO",
"dephead": "14",
"ref": "16",
"lemma": "|r\u00e4nta|",
"msd": "NN.UTR.SIN.IND.NOM",
"pos": "NN"
},
{
"word": "p\u00e5",
"deprel": "ET",
"dephead": "16",
"ref": "17",
"lemma": "|p\u00e5|",
"msd": "PP",
"pos": "PP"
},
{
"word": "13,5",
"deprel": "DT",
"dephead": "19",
"ref": "18",
"lemma": "|",
"msd": "RG.NOM",
"pos": "RG"
},
{
"word": "procent",
"deprel": "PA",
"dephead": "17",
"ref": "19",
"lemma": "|procent|",
"msd": "NN.UTR.PLU.IND.NOM",
"pos": "NN"
},
{
"word": "(",
"deprel": "IC",
"dephead": "19",
"ref": "20",
"lemma": "|",
"msd": "PAD",
"pos": "PAD"
},
{
"word": "!",
"deprel": "IU",
"dephead": "19",
"ref": "21",
"lemma": "|",
"msd": "MAD",
"pos": "MAD"
},
{
"word": ")",
"deprel": "IC",
"dephead": "19",
"ref": "22",
"lemma": "|",
"msd": "PAD",
"pos": "PAD"
}
]
},
{
"corpus": "DA",
"match": {
"position": 329943,
"start": 20,
"end": 22
},
"structs": {
"text_date": "2010-05-27 12:41:06",
"text_id": "7068",
"text_author": "Victor Bernhardtz"
},
"tokens": [
{
"word": "Det",
"deprel": "FS",
"dephead": "2",
"ref": "1",
"lemma": "|den|",
"msd": "PN.NEU.SIN.DEF.SUB+OBJ",
"pos": "PN"
},
{
"word": "\u00e4r",
"deprel": "ROOT",
"dephead": null,
"ref": "2",
"lemma": "|vara|",
"msd": "VB.PRS.AKT",
"pos": "VB"
},
{
"word": "tr\u00e5kigt",
"deprel": "CJ",
"dephead": "4",
"ref": "3",
"lemma": "|tr\u00e5kig|",
"msd": "JJ.POS.NEU.SIN.IND.NOM",
"pos": "JJ"
},
{
"word": "och",
"deprel": "SP",
"dephead": "2",
"ref": "4",
"lemma": "|och|",
"msd": "KN",
"pos": "KN"
},
{
"word": "dumt",
"deprel": "CJ",
"dephead": "4",
"ref": "5",
"lemma": "|dum|",
"msd": "JJ.POS.NEU.SIN.IND.NOM",
"pos": "JJ"
},
{
"word": "att",
"deprel": "ES",
"dephead": "2",
"ref": "6",
"lemma": "|att|",
"msd": "SN",
"pos": "SN"
},
{
"word": "Carlsson",
"deprel": "SS",
"dephead": "14",
"ref": "7",
"lemma": "|Carlsson|",
"msd": "PM.NOM",
"pos": "PM"
},
{
"word": "efter",
"deprel": "TA",
"dephead": "14",
"ref": "8",
"lemma": "|efter|",
"msd": "PP",
"pos": "PP"
},
{
"word": "fyra",
"deprel": "DT",
"dephead": "10",
"ref": "9",
"lemma": "|fyra|",
"msd": "RG.NOM",
"pos": "RG"
},
{
"word": "\u00e5r",
"deprel": "PA",
"dephead": "8",
"ref": "10",
"lemma": "|\u00e5r|",
"msd": "NN.NEU.PLU.IND.NOM",
"pos": "NN"
},
{
"word": "p\u00e5",
"deprel": "ET",
"dephead": "10",
"ref": "11",
"lemma": "|p\u00e5|",
"msd": "PP",
"pos": "PP"
},
{
"word": "jobbet",
"deprel": "PA",
"dephead": "11",
"ref": "12",
"lemma": "|jobb|",
"msd": "NN.NEU.SIN.DEF.NOM",
"pos": "NN"
},
{
"word": "inte",
"deprel": "NA",
"dephead": "14",
"ref": "13",
"lemma": "|inte|",
"msd": "AB",
"pos": "AB"
},
{
"word": "inser",
"deprel": "UA",
"dephead": "6",
"ref": "14",
"lemma": "|inse|",
"msd": "VB.PRS.AKT",
"pos": "VB"
},
{
"word": "att",
"deprel": "OO",
"dephead": "14",
"ref": "15",
"lemma": "|att|",
"msd": "SN",
"pos": "SN"
},
{
"word": "ingen",
"deprel": "DT",
"dephead": "18",
"ref": "16",
"lemma": "|ingen|",
"msd": "DT.UTR.SIN.IND",
"pos": "DT"
},
{
"word": "ny",
"deprel": "AT",
"dephead": "18",
"ref": "17",
"lemma": "|ny|",
"msd": "JJ.POS.UTR.SIN.IND.NOM",
"pos": "JJ"
},
{
"word": "generaldirekt\u00f6r",
"deprel": "SS",
"dephead": "21",
"ref": "18",
"lemma": "|generaldirekt\u00f6r|",
"msd": "NN.UTR.SIN.IND.NOM",
"pos": "NN"
},
{
"word": "i",
"deprel": "ET",
"dephead": "18",
"ref": "19",
"lemma": "|i|",
"msd": "PP",
"pos": "PP"
},
{
"word": "v\u00e4rlden",
"deprel": "PA",
"dephead": "19",
"ref": "20",
"lemma": "|v\u00e4rld|",
"msd": "NN.UTR.SIN.DEF.NOM",
"pos": "NN"
},
{
"word": "kommer",
"deprel": "UA",
"dephead": "15",
"ref": "21",
"lemma": "|komma|",
"msd": "VB.PRS.AKT",
"pos": "VB"
},
{
"word": "kunna",
"deprel": "VG",
"dephead": "21",
"ref": "22",
"lemma": "|kunna|",
"msd": "VB.INF.AKT",
"pos": "VB"
},
{
"word": "driva",
"deprel": "VG",
"dephead": "22",
"ref": "23",
"lemma": "|driva|",
"msd": "VB.INF.AKT",
"pos": "VB"
},
{
"word": "svenskt",
"deprel": "AT",
"dephead": "25",
"ref": "24",
"lemma": "|svensk|",
"msd": "JJ.POS.NEU.SIN.IND.NOM",
"pos": "JJ"
},
{
"word": "bist\u00e5nd",
"deprel": "OO",
"dephead": "23",
"ref": "25",
"lemma": "|bist\u00e5nd|",
"msd": "NN.NEU.SIN.IND.NOM",
"pos": "NN"
},
{
"word": "lika",
"deprel": "AA",
"dephead": "27",
"ref": "26",
"lemma": "|lika|",
"msd": "AB",
"pos": "AB"
},
{
"word": "effektivt",
"deprel": "AA",
"dephead": "23",
"ref": "27",
"lemma": "|effektiv|",
"msd": "AB.POS",
"pos": "AB"
},
{
"word": "som",
"deprel": "KA",
"dephead": "23",
"ref": "28",
"lemma": "|",
"msd": "KN",
"pos": "KN"
},
{
"word": "ett",
"deprel": "DT",
"dephead": "30",
"ref": "29",
"lemma": "|en|",
"msd": "DT.NEU.SIN.IND",
"pos": "DT"
},
{
"word": "f\u00f6retag",
"deprel": "UA",
"dephead": "28",
"ref": "30",
"lemma": "|f\u00f6retag|",
"msd": "NN.NEU.SIN.IND.NOM",
"pos": "NN"
},
{
"word": ".",
"deprel": "IP",
"dephead": "2",
"ref": "31",
"lemma": "|",
"msd": "MAD",
"pos": "MAD"
}
]
},
{
"corpus": "DA",
"match": {
"position": 331822,
"start": 2,
"end": 7
},
"structs": {
"text_date": "2010-05-18 12:56:41",
"text_id": "ledare-fornuftsfri-skolpolitik",
"text_author": "Victor Bernhardtz"
},
"tokens": [
{
"word": "Som",
"deprel": "MA",
"dephead": "3",
"ref": "1",
"lemma": "|",
"msd": "KN",
"pos": "KN"
},
{
"word": "bekant",
"deprel": "HD",
"dephead": "1",
"ref": "2",
"lemma": "|bekant|",
"msd": "JJ.POS.NEU.SIN.IND.NOM",
"pos": "JJ"
},
{
"word": "kommer",
"deprel": "ROOT",
"dephead": null,
"ref": "3",
"lemma": "|komma|",
"msd": "VB.PRS.AKT",
"pos": "VB"
},
{
"word": "den",
"deprel": "DT",
"dephead": "6",
"ref": "4",
"lemma": "|den|en|",
"msd": "DT.UTR.SIN.DEF",
"pos": "DT"
},
{
"word": "r\u00f6dgr\u00f6na",
"deprel": "AT",
"dephead": "6",
"ref": "5",
"lemma": "|r\u00f6dgr\u00f6n|",
"msd": "JJ.POS.UTR+NEU.SIN.DEF.NOM",
"pos": "JJ"
},
{
"word": "oppositionen",
"deprel": "SS",
"dephead": "3",
"ref": "6",
"lemma": "|opposition|",
"msd": "NN.UTR.SIN.DEF.NOM",
"pos": "NN"
},
{
"word": "riva",
"deprel": "VG",
"dephead": "3",
"ref": "7",
"lemma": "|riva|",
"msd": "VB.INF.AKT",
"pos": "VB"
},
{
"word": "upp",
"deprel": "PL",
"dephead": "7",
"ref": "8",
"lemma": "|upp|",
"msd": "PL",
"pos": "PL"
},
{
"word": "m\u00e5nga",
"deprel": "OO",
"dephead": "7",
"ref": "9",
"lemma": "|m\u00e5ngen|",
"msd": "PN.UTR+NEU.PLU.IND.SUB+OBJ",
"pos": "PN"
},
{
"word": "av",
"deprel": "ET",
"dephead": "9",
"ref": "10",
"lemma": "|av|",
"msd": "PP",
"pos": "PP"
},
{
"word": "Bj\u00f6rklunds",
"deprel": "DT",
"dephead": "12",
"ref": "11",
"lemma": "|Bj\u00f6rklund|",
"msd": "PM.GEN",
"pos": "PM"
},
{
"word": "reformer",
"deprel": "PA",
"dephead": "10",
"ref": "12",
"lemma": "|reform|",
"msd": "NN.UTR.PLU.IND.NOM",
"pos": "NN"
},
{
"word": ",",
"deprel": "IK",
"dephead": "7",
"ref": "13",
"lemma": "|",
"msd": "MID",
"pos": "MID"
},
{
"word": "om",
"deprel": "AA",
"dephead": "7",
"ref": "14",
"lemma": "|om|",
"msd": "SN",
"pos": "SN"
},
{
"word": "man",
"deprel": "SS",
"dephead": "16",
"ref": "15",
"lemma": "|man|",
"msd": "PN.UTR.SIN.IND.SUB",
"pos": "PN"
},
{
"word": "vinner",
"deprel": "UA",
"dephead": "14",
"ref": "16",
"lemma": "|vinna|",
"msd": "VB.PRS.AKT",
"pos": "VB"
},
{
"word": "valet",
"deprel": "OO",
"dephead": "16",
"ref": "17",
"lemma": "|val|",
"msd": "NN.NEU.SIN.DEF.NOM",
"pos": "NN"
},
{
"word": "i",
"deprel": "TA",
"dephead": "16",
"ref": "18",
"lemma": "|i|",
"msd": "PP",
"pos": "PP"
},
{
"word": "h\u00f6st",
"deprel": "HD",
"dephead": "18",
"ref": "19",
"lemma": "|h\u00f6st|",
"msd": "NN.UTR.SIN.IND.NOM",
"pos": "NN"
},
{
"word": ".",
"deprel": "IP",
"dephead": "3",
"ref": "20",
"lemma": "|",
"msd": "MAD",
"pos": "MAD"
}
]
},
{
"corpus": "DA",
"match": {
"position": 334385,
"start": 19,
"end": 21
},
"structs": {
"text_date": "2010-05-19 07:33:08",
"text_id": "ledare-det-tankte-vi-inte-pa",
"text_author": "Nisha Besara"
},
"tokens": [
{
"word": "Den",
"deprel": "DT",
"dephead": "3",
"ref": "1",
"lemma": "|den|en|",
"msd": "DT.UTR.SIN.DEF",
"pos": "DT"
},
{
"word": "borgerliga",
"deprel": "AT",
"dephead": "3",
"ref": "2",
"lemma": "|borgerlig|",
"msd": "JJ.POS.UTR+NEU.SIN.DEF.NOM",
"pos": "JJ"
},
{
"word": "regeringen",
"deprel": "SS",
"dephead": "4",
"ref": "3",
"lemma": "|regering|",
"msd": "NN.UTR.SIN.DEF.NOM",
"pos": "NN"
},
{
"word": "har",
"deprel": "ROOT",
"dephead": null,
"ref": "4",
"lemma": "|ha|",
"msd": "VB.PRS.AKT",
"pos": "VB"
},
{
"word": "beslutat",
"deprel": "VG",
"dephead": "4",
"ref": "5",
"lemma": "|besluta|",
"msd": "VB.SUP.AKT",
"pos": "VB"
},
{
"word": "l\u00e4gga",
"deprel": "OO",
"dephead": "5",
"ref": "6",
"lemma": "|l\u00e4gga|",
"msd": "VB.INF.AKT",
"pos": "VB"
},
{
"word": "28",
"deprel": "DT",
"dephead": "8",
"ref": "7",
"lemma": "|",
"msd": "RG.NOM",
"pos": "RG"
},
{
"word": "000",
"deprel": "DT",
"dephead": "9",
"ref": "8",
"lemma": "|",
"msd": "RG.NOM",
"pos": "RG"
},
{
"word": "000",
"deprel": "DT",
"dephead": "12",
"ref": "9",
"lemma": "|",
"msd": "RG.NOM",
"pos": "RG"
},
{
"word": "000",
"deprel": "DT",
"dephead": "12",
"ref": "10",
"lemma": "|",
"msd": "RG.NOM",
"pos": "RG"
},
{
"word": "svindlande",
"deprel": "AT",
"dephead": "12",
"ref": "11",
"lemma": "|svindla|svindlande|",
"msd": "PC.PRS.UTR+NEU.SIN+PLU.IND+DEF.NOM",
"pos": "PC"
},
{
"word": "kronor",
"deprel": "OO",
"dephead": "6",
"ref": "12",
"lemma": "|krona|",
"msd": "NN.UTR.PLU.IND.NOM",
"pos": "NN"
},
{
"word": "p\u00e5",
"deprel": "RA",
"dephead": "6",
"ref": "13",
"lemma": "|p\u00e5|",
"msd": "PP",
"pos": "PP"
},
{
"word": "en",
"deprel": "DT",
"dephead": "16",
"ref": "14",
"lemma": "|en|",
"msd": "DT.UTR.SIN.IND",
"pos": "DT"
},
{
"word": "fet",
"deprel": "AT",
"dephead": "16",
"ref": "15",
"lemma": "|fet|",
"msd": "JJ.POS.UTR.SIN.IND.NOM",
"pos": "JJ"
},
{
"word": "motorv\u00e4g",
"deprel": "PA",
"dephead": "13",
"ref": "16",
"lemma": "|motorv\u00e4g|",
"msd": "NN.UTR.SIN.IND.NOM",
"pos": "NN"
},
{
"word": ",",
"deprel": "IK",
"dephead": "16",
"ref": "17",
"lemma": "|",
"msd": "MID",
"pos": "MID"
},
{
"word": "som",
"deprel": "SS",
"dephead": "20",
"ref": "18",
"lemma": "|",
"msd": "HP.-.-.-",
"pos": "HP"
},
{
"word": "varken",
"deprel": "VA",
"dephead": "20",
"ref": "19",
"lemma": "|",
"msd": "KN",
"pos": "KN"
},
{
"word": "kommer",
"deprel": "MS",
"dephead": "23",
"ref": "20",
"lemma": "|komma|",
"msd": "VB.PRS.AKT",
"pos": "VB"
},
{
"word": "avlasta",
"deprel": "VG",
"dephead": "20",
"ref": "21",
"lemma": "|avlasta|",
"msd": "VB.INF.AKT",
"pos": "VB"
},
{
"word": "innerstaden",
"deprel": "OO",
"dephead": "21",
"ref": "22",
"lemma": "|innerstad|",
"msd": "NN.UTR.SIN.DEF.NOM",
"pos": "NN"
},
{
"word": "eller",
"deprel": "ET",
"dephead": "16",
"ref": "23",
"lemma": "|eller|",
"msd": "KN",
"pos": "KN"
},
{
"word": "ha",
"deprel": "+F",
"dephead": "23",
"ref": "24",
"lemma": "|ha|",
"msd": "VB.INF.AKT",
"pos": "VB"
},
{
"word": "s\u00e4rskilda",
"deprel": "AT",
"dephead": "26",
"ref": "25",
"lemma": "|s\u00e4rskild|s\u00e4rskilja|",
"msd": "PC.PRF.UTR+NEU.PLU.IND+DEF.NOM",
"pos": "PC"
},
{
"word": "bussfiler",
"deprel": "OO",
"dephead": "24",
"ref": "26",
"lemma": "|bussfil|",
"msd": "NN.UTR.PLU.IND.NOM",
"pos": "NN"
},
{
"word": "eller",
"deprel": "++",
"dephead": "23",
"ref": "27",
"lemma": "|eller|",
"msd": "KN",
"pos": "KN"
},
{
"word": "hj\u00e4lpa",
"deprel": "+F",
"dephead": "27",
"ref": "28",
"lemma": "|hj\u00e4lpa|",
"msd": "VB.INF.AKT",
"pos": "VB"
},
{
"word": "Sverige",
"deprel": "OO",
"dephead": "28",
"ref": "29",
"lemma": "|Sverige|",
"msd": "PM.NOM",
"pos": "PM"
},
{
"word": "(",
"deprel": "IR",
"dephead": "28",
"ref": "30",
"lemma": "|",
"msd": "PAD",
"pos": "PAD"
},
{
"word": "utan",
"deprel": "+F",
"dephead": "27",
"ref": "31",
"lemma": "|utan|",
"msd": "KN",
"pos": "KN"
},
{
"word": "stj\u00e4lpa",
"deprel": "+F",
"dephead": "31",
"ref": "32",
"lemma": "|stj\u00e4lpa|",
"msd": "VB.INF.AKT",
"pos": "VB"
},
{
"word": ")",
"deprel": "JR",
"dephead": "32",
"ref": "33",
"lemma": "|",
"msd": "PAD",
"pos": "PAD"
},
{
"word": "att",
"deprel": "OA",
"dephead": "32",
"ref": "34",
"lemma": "|att|",
"msd": "IE",
"pos": "IE"
},
{
"word": "n\u00e5",
"deprel": "IF",
"dephead": "34",
"ref": "35",
"lemma": "|n\u00e5|",
"msd": "VB.INF.AKT",
"pos": "VB"
},
{
"word": "milj\u00f6m\u00e5len",
"deprel": "OO",
"dephead": "35",
"ref": "36",
"lemma": "|milj\u00f6m\u00e5l|",
"msd": "NN.NEU.PLU.DEF.NOM",
"pos": "NN"
},
{
"word": ".",
"deprel": "IP",
"dephead": "4",
"ref": "37",
"lemma": "|",
"msd": "MAD",
"pos": "MAD"
}
]
},
{
"corpus": "DA",
"match": {
"position": 347741,
"start": 7,
"end": 13
},
"structs": {
"text_date": "2010-05-10 14:37:22",
"text_id": "editorial-morkbla-tongangar",
"text_author": "Yonna Waltersson"
},
"tokens": [
{
"word": "M\u00e4nniskor",
"deprel": "SS",
"dephead": "8",
"ref": "1",
"lemma": "|m\u00e4nniska|",
"msd": "NN.UTR.PLU.IND.NOM",
"pos": "NN"
},
{
"word": "som",
"deprel": "SS",
"dephead": "3",
"ref": "2",
"lemma": "|",
"msd": "HP.-.-.-",
"pos": "HP"
},
{
"word": "dr\u00f6mmer",
"deprel": "ET",
"dephead": "1",
"ref": "3",
"lemma": "|dr\u00f6mma|",
"msd": "VB.PRS.AKT",
"pos": "VB"
},
{
"word": "om",
"deprel": "OA",
"dephead": "3",
"ref": "4",
"lemma": "|om|",
"msd": "PP",
"pos": "PP"
},
{
"word": "ett",
"deprel": "DT",
"dephead": "7",
"ref": "5",
"lemma": "|en|",
"msd": "DT.NEU.SIN.IND",
"pos": "DT"
},
{
"word": "b\u00e4ttre",
"deprel": "AT",
"dephead": "7",
"ref": "6",
"lemma": "|bra|god|",
"msd": "JJ.KOM.UTR+NEU.SIN+PLU.IND+DEF.NOM",
"pos": "JJ"
},
{
"word": "liv",
"deprel": "PA",
"dephead": "4",
"ref": "7",
"lemma": "|liv|",
"msd": "NN.NEU.SIN.IND.NOM",
"pos": "NN"
},
{
"word": "kommer",
"deprel": "MS",
"dephead": "19",
"ref": "8",
"lemma": "|komma|",
"msd": "VB.PRS.AKT",
"pos": "VB"
},
{
"word": "aldrig",
"deprel": "TA",
"dephead": "8",
"ref": "9",
"lemma": "|aldrig|",
"msd": "AB",
"pos": "AB"
},
{
"word": "med",
"deprel": "AA",
"dephead": "8",
"ref": "10",
"lemma": "|med|",
"msd": "PP",
"pos": "PP"
},
{
"word": "f\u00f6rbud",
"deprel": "PA",
"dephead": "10",
"ref": "11",
"lemma": "|f\u00f6rbud|",
"msd": "NN.NEU.SIN.IND.NOM",
"pos": "NN"
},
{
"word": "att",
"deprel": "ET",
"dephead": "11",
"ref": "12",
"lemma": "|att|",
"msd": "IE",
"pos": "IE"
},
{
"word": "kunna",
"deprel": "IF",
"dephead": "12",
"ref": "13",
"lemma": "|kunna|",
"msd": "VB.INF.AKT",
"pos": "VB"
},
{
"word": "h\u00e5llas",
"deprel": "VG",
"dephead": "13",
"ref": "14",
"lemma": "|h\u00e5lla|h\u00e5llas|",
"msd": "VB.INF.SFO",
"pos": "VB"
},
{
"word": "borta",
"deprel": "PL",
"dephead": "14",
"ref": "15",
"lemma": "|borta|",
"msd": "PL",
"pos": "PL"
},
{
"word": "fr\u00e5n",
"deprel": "RA",
"dephead": "14",
"ref": "16",
"lemma": "|fr\u00e5n|",
"msd": "PP",
"pos": "PP"
},
{
"word": "Sverige",
"deprel": "PA",
"dephead": "16",
"ref": "17",
"lemma": "|Sverige|",
"msd": "PM.NOM",
"pos": "PM"
},
{
"word": ",",
"deprel": "IK",
"dephead": "19",
"ref": "18",
"lemma": "|",
"msd": "MID",
"pos": "MID"
},
{
"word": "men",
"deprel": "ROOT",
"dephead": null,
"ref": "19",
"lemma": "|men|",
"msd": "KN",
"pos": "KN"
},
{
"word": "det",
"deprel": "SS",
"dephead": "21",
"ref": "20",
"lemma": "|den|",
"msd": "PN.NEU.SIN.DEF.SUB+OBJ",
"pos": "PN"
},
{
"word": "\u00e4r",
"deprel": "MS",
"dephead": "19",
"ref": "21",
"lemma": "|vara|",
"msd": "VB.PRS.AKT",
"pos": "VB"
},
{
"word": "en",
"deprel": "DT",
"dephead": "23",
"ref": "22",
"lemma": "|en|",
"msd": "DT.UTR.SIN.IND",
"pos": "DT"
},
{
"word": "insikt",
"deprel": "SP",
"dephead": "21",
"ref": "23",
"lemma": "|insikt|",
"msd": "NN.UTR.SIN.IND.NOM",
"pos": "NN"
},
{
"word": "som",
"deprel": "SS",
"dephead": "25",
"ref": "24",
"lemma": "|",
"msd": "HP.-.-.-",
"pos": "HP"
},
{
"word": "verkar",
"deprel": "ET",
"dephead": "23",
"ref": "25",
"lemma": "|verka|",
"msd": "VB.PRS.AKT",
"pos": "VB"
},
{
"word": "vara",
"deprel": "VG",
"dephead": "25",
"ref": "26",
"lemma": "|vara|",
"msd": "VB.INF.AKT",
"pos": "VB"
},
{
"word": "l\u00e5ngt",
"deprel": "AA",
"dephead": "28",
"ref": "27",
"lemma": "|l\u00e5ng|l\u00e5ngt|",
"msd": "AB.POS",
"pos": "AB"
},
{
"word": "bort",
"deprel": "RA",
"dephead": "26",
"ref": "28",
"lemma": "|bort|",
"msd": "AB",
"pos": "AB"
},
{
"word": "i",
"deprel": "RA",
"dephead": "28",
"ref": "29",
"lemma": "|i|",
"msd": "PP",
"pos": "PP"
},
{
"word": "de",
"deprel": "DT",
"dephead": "32",
"ref": "30",
"lemma": "|en|",
"msd": "DT.UTR+NEU.PLU.DEF",
"pos": "DT"
},
{
"word": "wagerska",
"deprel": "AT",
"dephead": "32",
"ref": "31",
"lemma": "|",
"msd": "JJ.POS.UTR+NEU.PLU.IND+DEF.NOM",
"pos": "JJ"
},
{
"word": "tankebanorna",
"deprel": "PA",
"dephead": "29",
"ref": "32",
"lemma": "|tankebana|",
"msd": "NN.UTR.PLU.DEF.NOM",
"pos": "NN"
},
{
"word": ".",
"deprel": "IP",
"dephead": "19",
"ref": "33",
"lemma": "|",
"msd": "MAD",
"pos": "MAD"
}
]
},
{
"corpus": "DA",
"match": {
"position": 350625,
"start": 21,
"end": 24
},
"structs": {
"text_date": "2010-05-11 20:16:13",
"text_id": "reportage-efter-oljan",
"text_author": "Anna Hellgren"
},
"tokens": [
{
"word": "Katastrofen",
"deprel": "SS",
"dephead": "5",
"ref": "1",
"lemma": "|katastrof|",
"msd": "NN.UTR.SIN.DEF.NOM",
"pos": "NN"
},
{
"word": "i",
"deprel": "ET",
"dephead": "1",
"ref": "2",
"lemma": "|i|",
"msd": "PP",
"pos": "PP"
},
{
"word": "Mexikanska",
"deprel": "PA",
"dephead": "2",
"ref": "3",
"lemma": "|mexikansk|",
"msd": "JJ.POS.UTR+NEU.SIN.DEF.NOM",
"pos": "JJ"
},
{
"word": "golfen",
"deprel": "HD",
"dephead": "3",
"ref": "4",
"lemma": "|golf|",
"msd": "NN.UTR.SIN.DEF.NOM",
"pos": "NN"
},
{
"word": "borde",
"deprel": "ROOT",
"dephead": null,
"ref": "5",
"lemma": "|b\u00f6ra|",
"msd": "VB.PRT.AKT",
"pos": "VB"
},
{
"word": "s\u00e5ledes",
"deprel": "+A",
"dephead": "5",
"ref": "6",
"lemma": "|s\u00e5ledes|",
"msd": "AB",
"pos": "AB"
},
{
"word": "ses",
"deprel": "VG",
"dephead": "5",
"ref": "7",
"lemma": "|se|",
"msd": "VB.INF.SFO",
"pos": "VB"
},
{
"word": "f\u00f6r",
"deprel": "OA",
"dephead": "7",
"ref": "8",
"lemma": "|f\u00f6r|",
"msd": "PP",
"pos": "PP"
},
{
"word": "vad",
"deprel": "PA",
"dephead": "8",
"ref": "9",
"lemma": "|vad|",
"msd": "HP.NEU.SIN.IND",
"pos": "HP"
},
{
"word": "den",
"deprel": "SS",
"dephead": "11",
"ref": "10",
"lemma": "|den|",
"msd": "PN.UTR.SIN.DEF.SUB+OBJ",
"pos": "PN"
},
{
"word": "\u00e4r",
"deprel": "PA",
"dephead": "8",
"ref": "11",
"lemma": "|vara|",
"msd": "VB.PRS.AKT",
"pos": "VB"
},
{
"word": ":",
"deprel": "IQ",
"dephead": "9",
"ref": "12",
"lemma": "|",
"msd": "MID",
"pos": "MID"
},
{
"word": "Ett",
"deprel": "DT",
"dephead": "14",
"ref": "13",
"lemma": "|en|",
"msd": "DT.NEU.SIN.IND",
"pos": "DT"
},
{
"word": "underk\u00e4nnande",
"deprel": "AN",
"dephead": "9",
"ref": "14",
"lemma": "|underk\u00e4nnande|",
"msd": "NN.NEU.SIN.IND.NOM",
"pos": "NN"
},
{
"word": "av",
"deprel": "ET",
"dephead": "14",
"ref": "15",
"lemma": "|av|",
"msd": "PP",
"pos": "PP"
},
{
"word": "de",
"deprel": "DT",
"dephead": "17",
"ref": "16",
"lemma": "|en|",
"msd": "DT.UTR+NEU.PLU.DEF",
"pos": "DT"
},
{
"word": "kapitalkramare",
"deprel": "PA",
"dephead": "15",
"ref": "17",
"lemma": "|",
"msd": "NN.UTR.PLU.IND.NOM",
"pos": "NN"
},
{
"word": "som",
"deprel": "SS",
"dephead": "19",
"ref": "18",
"lemma": "|",
"msd": "HP.-.-.-",
"pos": "HP"
},
{
"word": "h\u00e4vdar",
"deprel": "ET",
"dephead": "17",
"ref": "19",
"lemma": "|h\u00e4vda|",
"msd": "VB.PRS.AKT",
"pos": "VB"
},
{
"word": "att",
"deprel": "OO",
"dephead": "19",
"ref": "20",
"lemma": "|att|",
"msd": "SN",
"pos": "SN"
},
{
"word": "marknaden",
"deprel": "SS",
"dephead": "22",
"ref": "21",
"lemma": "|marknad|",
"msd": "NN.UTR.SIN.DEF.NOM",
"pos": "NN"
},
{
"word": "kommer",
"deprel": "UA",
"dephead": "20",
"ref": "22",
"lemma": "|komma|",
"msd": "VB.PRS.AKT",
"pos": "VB"
},
{
"word": "att",
"deprel": "VG",
"dephead": "22",
"ref": "23",
"lemma": "|att|",
"msd": "IE",
"pos": "IE"
},
{
"word": "l\u00f6sa",
"deprel": "IF",
"dephead": "23",
"ref": "24",
"lemma": "|l\u00f6sa|",
"msd": "VB.INF.AKT",
"pos": "VB"
},
{
"word": "s\u00e5v\u00e4l",
"deprel": "VA",
"dephead": "29",
"ref": "25",
"lemma": "|s\u00e5v\u00e4l_som|",
"msd": "KN",
"pos": "KN"
},
{
"word": "klimat-",
"deprel": "CJ",
"dephead": "29",
"ref": "26",
"lemma": "|klimat|",
"msd": "NN.UTR.-.-.SMS",
"pos": "NN"
},
{
"word": "som",
"deprel": "CJ",
"dephead": "29",
"ref": "27",
"lemma": "|s\u00e5v\u00e4l_som:25|",
"msd": "KN",
"pos": "KN"
},
{
"word": "energikris",
"deprel": "UA",
"dephead": "27",
"ref": "28",
"lemma": "|energikris|",
"msd": "NN.UTR.SIN.IND.NOM",
"pos": "NN"
},
{
"word": "och",
"deprel": "OO",
"dephead": "24",
"ref": "29",
"lemma": "|och|",
"msd": "KN",
"pos": "KN"
},
{
"word": "en",
"deprel": "DT",
"dephead": "32",
"ref": "30",
"lemma": "|en|",
"msd": "DT.UTR.SIN.IND",
"pos": "DT"
},
{
"word": "alarmerande",
"deprel": "AT",
"dephead": "32",
"ref": "31",
"lemma": "|alarmera|alarmerande|",
"msd": "PC.PRS.UTR+NEU.SIN+PLU.IND+DEF.NOM",
"pos": "PC"
},
{
"word": "uppmaning",
"deprel": "CJ",
"dephead": "29",
"ref": "32",
"lemma": "|uppmaning|",
"msd": "NN.UTR.SIN.IND.NOM",
"pos": "NN"
},
{
"word": "till",
"deprel": "ET",
"dephead": "32",
"ref": "33",
"lemma": "|till|",
"msd": "PP",
"pos": "PP"
},
{
"word": "att",
"deprel": "PA",
"dephead": "33",
"ref": "34",
"lemma": "|att|",
"msd": "IE",
"pos": "IE"
},
{
"word": "p\u00e5",
"deprel": "AA",
"dephead": "37",
"ref": "35",
"lemma": "|p\u00e5|p\u00e5_allvar|",
"msd": "PP",
"pos": "PP"
},
{
"word": "allvar",
"deprel": "PA",
"dephead": "35",
"ref": "36",
"lemma": "|allvar|p\u00e5_allvar:35|",
"msd": "NN.NEU.SIN.IND.NOM",
"pos": "NN"
},
{
"word": "b\u00f6rja",
"deprel": "IF",
"dephead": "34",
"ref": "37",
"lemma": "|b\u00f6rja|",
"msd": "VB.INF.AKT",
"pos": "VB"
},
{
"word": "omst\u00e4llningen",
"deprel": "OO",
"dephead": "37",
"ref": "38",
"lemma": "|omst\u00e4llning|",
"msd": "NN.UTR.SIN.DEF.NOM",
"pos": "NN"
},
{
"word": "till",
"deprel": "OA",
"dephead": "37",
"ref": "39",
"lemma": "|till|",
"msd": "PP",
"pos": "PP"
},
{
"word": "ett",
"deprel": "DT",
"dephead": "41",
"ref": "40",
"lemma": "|en|",
"msd": "DT.NEU.SIN.IND",
"pos": "DT"
},
{
"word": "samh\u00e4lle",
"deprel": "PA",
"dephead": "39",
"ref": "41",
"lemma": "|samh\u00e4lle|",
"msd": "NN.NEU.SIN.IND.NOM",
"pos": "NN"
},
{
"word": "utan",
"deprel": "AA",
"dephead": "37",
"ref": "42",
"lemma": "|utan|",
"msd": "PP",
"pos": "PP"
},
{
"word": "oljeberoende",
"deprel": "PA",
"dephead": "42",
"ref": "43",
"lemma": "|oljeberoende|",
"msd": "NN.NEU.SIN.IND.NOM",
"pos": "NN"
},
{
"word": ".",
"deprel": "IP",
"dephead": "5",
"ref": "44",
"lemma": "|",
"msd": "MAD",
"pos": "MAD"
}
]
},
{
"corpus": "DA",
"match": {
"position": 350668,
"start": 20,
"end": 22
},
"structs": {
"text_date": "2010-05-11 20:16:13",
"text_id": "reportage-efter-oljan",
"text_author": "Anna Hellgren"
},
"tokens": [
{
"word": "Det",
"deprel": "FS",
"dephead": "2",
"ref": "1",
"lemma": "|den|",
"msd": "PN.NEU.SIN.DEF.SUB+OBJ",
"pos": "PN"
},
{
"word": "kr\u00e4vs",
"deprel": "ROOT",
"dephead": null,
"ref": "2",
"lemma": "|kr\u00e4va|kr\u00e4vas|",
"msd": "VB.PRS.SFO",
"pos": "VB"
},
{
"word": "ingen",
"deprel": "DT",
"dephead": "5",
"ref": "3",
"lemma": "|ingen|",
"msd": "DT.UTR.SIN.IND",
"pos": "DT"
},
{
"word": "st\u00f6rre",
"deprel": "AT",
"dephead": "5",
"ref": "4",
"lemma": "|stor|",
"msd": "JJ.KOM.UTR+NEU.SIN+PLU.IND+DEF.NOM",
"pos": "JJ"
},
{
"word": "fantasi",
"deprel": "ES",
"dephead": "2",
"ref": "5",
"lemma": "|fantasi|",
"msd": "NN.UTR.SIN.IND.NOM",
"pos": "NN"
},
{
"word": "att",
"deprel": "ES",
"dephead": "2",
"ref": "6",
"lemma": "|att|",
"msd": "IE",
"pos": "IE"
},
{
"word": "f\u00f6rest\u00e4lla",
"deprel": "IF",
"dephead": "6",
"ref": "7",
"lemma": "|f\u00f6rest\u00e4lla|f\u00f6rest\u00e4lla_sig|",
"msd": "VB.INF.AKT",
"pos": "VB"
},
{
"word": "sig",
"deprel": "IO",
"dephead": "7",
"ref": "8",
"lemma": "|sig|f\u00f6rest\u00e4lla_sig:7|",
"msd": "PN.UTR+NEU.SIN+PLU.DEF.OBJ",
"pos": "PN"
},
{
"word": "den",
"deprel": "DT",
"dephead": "11",
"ref": "9",
"lemma": "|den|en|",
"msd": "DT.UTR.SIN.DEF",
"pos": "DT"
},
{
"word": "globala",
"deprel": "AT",
"dephead": "11",
"ref": "10",
"lemma": "|global|",
"msd": "JJ.POS.UTR+NEU.SIN.DEF.NOM",
"pos": "JJ"
},
{
"word": "depression",
"deprel": "OO",
"dephead": "7",
"ref": "11",
"lemma": "|depression|",
"msd": "NN.UTR.SIN.IND.NOM",
"pos": "NN"
},
{
"word": "som",
"deprel": "OO",
"dephead": "14",
"ref": "12",
"lemma": "|",
"msd": "HP.-.-.-",
"pos": "HP"
},
{
"word": "v\u00e4rlden",
"deprel": "SS",
"dephead": "14",
"ref": "13",
"lemma": "|v\u00e4rld|",
"msd": "NN.UTR.SIN.DEF.NOM",
"pos": "NN"
},
{
"word": "\u2013",
"deprel": "ET",
"dephead": "11",
"ref": "14",
"lemma": "|",
"msd": "VB.PRS.AKT",
"pos": "VB"
},
{
"word": "utan",
"deprel": "AA",
"dephead": "14",
"ref": "15",
"lemma": "|utan|",
"msd": "PP",
"pos": "PP"
},
{
"word": "alternativa",
"deprel": "AT",
"dephead": "18",
"ref": "16",
"lemma": "|alternativ|",
"msd": "JJ.POS.UTR+NEU.PLU.IND+DEF.NOM",
"pos": "JJ"
},
{
"word": "energik\u00e4llor",
"deprel": "CJ",
"dephead": "18",
"ref": "17",
"lemma": "|energik\u00e4lla|",
"msd": "NN.UTR.PLU.IND.NOM",
"pos": "NN"
},
{
"word": "och",
"deprel": "PA",
"dephead": "15",
"ref": "18",
"lemma": "|och|",
"msd": "KN",
"pos": "KN"
},
{
"word": "levnadsvanor",
"deprel": "CJ",
"dephead": "18",
"ref": "19",
"lemma": "|levnadsvana|",
"msd": "NN.UTR.PLU.IND.NOM",
"pos": "NN"
},
{
"word": "\u2013",
"deprel": "SS",
"dephead": "21",
"ref": "20",
"lemma": "|",
"msd": "HP.-.-.-",
"pos": "HP"
},
{
"word": "kommer",
"deprel": "ET",
"dephead": "11",
"ref": "21",
"lemma": "|komma|",
"msd": "VB.PRS.AKT",
"pos": "VB"
},
{
"word": "kastas",
"deprel": "VG",
"dephead": "21",
"ref": "22",
"lemma": "|kasta|",
"msd": "VB.INF.SFO",
"pos": "VB"
},
{
"word": "ner",
"deprel": "PL",
"dephead": "22",
"ref": "23",
"lemma": "|ner|",
"msd": "PL",
"pos": "PL"
},
{
"word": "i",
"deprel": "TA",
"dephead": "22",
"ref": "24",
"lemma": "|i|",
"msd": "PP",
"pos": "PP"
},
{
"word": "den",
"deprel": "DT",
"dephead": "26",
"ref": "25",
"lemma": "|den|en|",
"msd": "DT.UTR.SIN.DEF",
"pos": "DT"
},
{
"word": "dagen",
"deprel": "PA",
"dephead": "24",
"ref": "26",
"lemma": "|dag|",
"msd": "NN.UTR.SIN.DEF.NOM",
"pos": "NN"
},
{
"word": "oljan",
"deprel": "SS",
"dephead": "28",
"ref": "27",
"lemma": "|olja|",
"msd": "NN.UTR.SIN.DEF.NOM",
"pos": "NN"
},
{
"word": "b\u00f6rjar",
"deprel": "ET",
"dephead": "26",
"ref": "28",
"lemma": "|b\u00f6rja|",
"msd": "VB.PRS.AKT",
"pos": "VB"
},
{
"word": "sina",
"deprel": "OO",
"dephead": "28",
"ref": "29",
"lemma": "|sig|",
"msd": "PS.UTR+NEU.PLU.DEF",
"pos": "PS"
},
{
"word": ".",
"deprel": "IP",
"dephead": "2",
"ref": "30",
"lemma": "|",
"msd": "MAD",
"pos": "MAD"
}
]
},
{
"corpus": "DA",
"match": {
"position": 354196,
"start": 1,
"end": 5
},
"structs": {
"text_date": "2010-05-03 22:49:51",
"text_id": "coverage-akad-jamlikhet-vantar",
"text_author": "Bj\u00f6rn Elmbrant"
},
"tokens": [
{
"word": "Naturligtvis",
"deprel": "MA",
"dephead": "2",
"ref": "1",
"lemma": "|naturligtvis|",
"msd": "AB",
"pos": "AB"
},
{
"word": "kommer",
"deprel": "ROOT",
"dephead": null,
"ref": "2",
"lemma": "|komma|",
"msd": "VB.PRS.AKT",
"pos": "VB"
},
{
"word": "det",
"deprel": "FS",
"dephead": "2",
"ref": "3",
"lemma": "|den|",
"msd": "PN.NEU.SIN.DEF.SUB+OBJ",
"pos": "PN"
},
{
"word": "att",
"deprel": "VG",
"dephead": "2",
"ref": "4",
"lemma": "|att|",
"msd": "IE",
"pos": "IE"
},
{
"word": "finnas",
"deprel": "IF",
"dephead": "4",
"ref": "5",
"lemma": "|finna|finnas|",
"msd": "VB.INF.SFO",
"pos": "VB"
},
{
"word": "de",
"deprel": "ES",
"dephead": "5",
"ref": "6",
"lemma": "|de|",
"msd": "PN.UTR+NEU.PLU.DEF.SUB",
"pos": "PN"
},
{
"word": "som",
"deprel": "SS",
"dephead": "8",
"ref": "7",
"lemma": "|",
"msd": "HP.-.-.-",
"pos": "HP"
},
{
"word": "menar",
"deprel": "ET",
"dephead": "6",
"ref": "8",
"lemma": "|mena|",
"msd": "VB.PRS.AKT",
"pos": "VB"
},
{
"word": "att",
"deprel": "OO",
"dephead": "8",
"ref": "9",
"lemma": "|att|",
"msd": "SN",
"pos": "SN"
},
{
"word": "de",
"deprel": "DT",
"dephead": "11",
"ref": "10",
"lemma": "|en|",
"msd": "DT.UTR+NEU.PLU.DEF",
"pos": "DT"
},
{
"word": "r\u00f6dgr\u00f6na",
"deprel": "SS",
"dephead": "12",
"ref": "11",
"lemma": "|r\u00f6dgr\u00f6n|",
"msd": "JJ.POS.UTR+NEU.PLU.IND+DEF.NOM",
"pos": "JJ"
},
{
"word": "kunnat",
"deprel": "UA",
"dephead": "9",
"ref": "12",
"lemma": "|kunna|",
"msd": "VB.SUP.AKT",
"pos": "VB"
},
{
"word": "utmana",
"deprel": "VG",
"dephead": "12",
"ref": "13",
"lemma": "|utmana|",
"msd": "VB.INF.AKT",
"pos": "VB"
},
{
"word": "medelklassv\u00e4ljarna",
"deprel": "OO",
"dephead": "13",
"ref": "14",
"lemma": "|medelklassv\u00e4ljare|",
"msd": "NN.UTR.PLU.DEF.NOM",
"pos": "NN"
},
{
"word": "mer",
"deprel": "AA",
"dephead": "13",
"ref": "15",
"lemma": "|mer|mycket|",
"msd": "AB.KOM",
"pos": "AB"
},
{
"word": ".",
"deprel": "IP",
"dephead": "2",
"ref": "16",
"lemma": "|",
"msd": "MAD",
"pos": "MAD"
}
]
},
{
"corpus": "DA",
"match": {
"position": 354612,
"start": 4,
"end": 7
},
"structs": {
"text_date": "2010-05-19 12:41:52",
"text_id": "reportage-mp-har-gjort-ett-val-samarbetet-ar-logiskt",
"text_author": "H\u00e5kan A Bengtsson"
},
"tokens": [
{
"word": "Men",
"deprel": "ROOT",
"dephead": null,
"ref": "1",
"lemma": "|men|",
"msd": "KN",
"pos": "KN"
},
{
"word": "v\u00e4nster",
"deprel": "CJ",
"dephead": "3",
"ref": "2",
"lemma": "|v\u00e4nster|",
"msd": "NN.UTR.SIN.IND.NOM",
"pos": "NN"
},
{
"word": "och",
"deprel": "SS",
"dephead": "5",
"ref": "3",
"lemma": "|och|",
"msd": "KN",
"pos": "KN"
},
{
"word": "h\u00f6ger",
"deprel": "CJ",
"dephead": "3",
"ref": "4",
"lemma": "|h\u00f6ger|",
"msd": "NN.UTR.SIN.IND.NOM",
"pos": "NN"
},
{
"word": "kommer",
"deprel": "MS",
"dephead": "1",
"ref": "5",
"lemma": "|komma|",
"msd": "VB.PRS.AKT",
"pos": "VB"
},
{
"word": "att",
"deprel": "VG",
"dephead": "5",
"ref": "6",
"lemma": "|att|",
"msd": "IE",
"pos": "IE"
},
{
"word": "forts\u00e4tta",
"deprel": "IF",
"dephead": "6",
"ref": "7",
"lemma": "|forts\u00e4tta|",
"msd": "VB.INF.AKT",
"pos": "VB"
},
{
"word": "att",
"deprel": "OO",
"dephead": "7",
"ref": "8",
"lemma": "|att|",
"msd": "IE",
"pos": "IE"
},
{
"word": "definiera",
"deprel": "IF",
"dephead": "8",
"ref": "9",
"lemma": "|definiera|",
"msd": "VB.INF.AKT",
"pos": "VB"
},
{
"word": "grundkonflikten",
"deprel": "OO",
"dephead": "9",
"ref": "10",
"lemma": "|grundkonflikt|",
"msd": "NN.UTR.SIN.DEF.NOM",
"pos": "NN"
},
{
"word": "i",
"deprel": "ET",
"dephead": "10",
"ref": "11",
"lemma": "|i|",
"msd": "PP",
"pos": "PP"
},
{
"word": "svensk",
"deprel": "AT",
"dephead": "13",
"ref": "12",
"lemma": "|svensk|",
"msd": "JJ.POS.UTR.SIN.IND.NOM",
"pos": "JJ"
},
{
"word": "politik",
"deprel": "PA",
"dephead": "11",
"ref": "13",
"lemma": "|politik|",
"msd": "NN.UTR.SIN.IND.NOM",
"pos": "NN"
},
{
"word": ".",
"deprel": "IP",
"dephead": "5",
"ref": "14",
"lemma": "|",
"msd": "MAD",
"pos": "MAD"
}
]
},
{
"corpus": "DA",
"match": {
"position": 357038,
"start": 12,
"end": 18
},
"structs": {
"text_date": "2010-05-26 15:13:04",
"text_id": "7038",
"text_author": "Magnus \u00c5sblad"
},
"tokens": [
{
"word": "Det",
"deprel": "PA",
"dephead": "8",
"ref": "1",
"lemma": "|den|",
"msd": "PN.NEU.SIN.DEF.SUB+OBJ",
"pos": "PN"
},
{
"word": "kan",
"deprel": "ROOT",
"dephead": null,
"ref": "2",
"lemma": "|kunna|",
"msd": "VB.PRS.AKT",
"pos": "VB"
},
{
"word": "man",
"deprel": "SS",
"dephead": "2",
"ref": "3",
"lemma": "|man|",
"msd": "PN.UTR.SIN.IND.SUB",
"pos": "PN"
},
{
"word": "tycka",
"deprel": "VG",
"dephead": "2",
"ref": "4",
"lemma": "|tycka|",
"msd": "VB.INF.AKT",
"pos": "VB"
},
{
"word": "vad",
"deprel": "PA",
"dephead": "8",
"ref": "5",
"lemma": "|vad|",
"msd": "HP.NEU.SIN.IND",
"pos": "HP"
},
{
"word": "man",
"deprel": "SS",
"dephead": "7",
"ref": "6",
"lemma": "|man|",
"msd": "PN.UTR.SIN.IND.SUB",
"pos": "PN"
},
{
"word": "vill",
"deprel": "OO",
"dephead": "4",
"ref": "7",
"lemma": "|vilja|",
"msd": "VB.PRS.AKT",
"pos": "VB"
},
{
"word": "om",
"deprel": "OA",
"dephead": "7",
"ref": "8",
"lemma": "|om|",
"msd": "PP",
"pos": "PP"
},
{
"word": "\u2013",
"deprel": "PA",
"dephead": "8",
"ref": "9",
"lemma": "|",
"msd": "MID",
"pos": "MID"
},
{
"word": "men",
"deprel": "OO",
"dephead": "4",
"ref": "10",
"lemma": "|men|",
"msd": "KN",
"pos": "KN"
},
{
"word": "om",
"deprel": "CJ",
"dephead": "10",
"ref": "11",
"lemma": "|om|",
"msd": "SN",
"pos": "SN"
},
{
"word": "riksdagsvalet",
"deprel": "SS",
"dephead": "13",
"ref": "12",
"lemma": "|riksdagsval|",
"msd": "NN.NEU.SIN.DEF.NOM",
"pos": "NN"
},
{
"word": "kommer",
"deprel": "UA",
"dephead": "11",
"ref": "13",
"lemma": "|komma|",
"msd": "VB.PRS.AKT",
"pos": "VB"
},
{
"word": "att",
"deprel": "VG",
"dephead": "13",
"ref": "14",
"lemma": "|att|",
"msd": "IE",
"pos": "IE"
},
{
"word": "handlar",
"deprel": "IF",
"dephead": "14",
"ref": "15",
"lemma": "|handla|",
"msd": "VB.PRS.AKT",
"pos": "VB"
},
{
"word": "om",
"deprel": "OA",
"dephead": "15",
"ref": "16",
"lemma": "|om|",
"msd": "PP",
"pos": "PP"
},
{
"word": "att",
"deprel": "PA",
"dephead": "16",
"ref": "17",
"lemma": "|att|",
"msd": "IE",
"pos": "IE"
},
{
"word": "blidka",
"deprel": "IF",
"dephead": "17",
"ref": "18",
"lemma": "|blidka|",
"msd": "VB.INF.AKT",
"pos": "VB"
},
{
"word": "en",
"deprel": "DT",
"dephead": "20",
"ref": "19",
"lemma": "|en|",
"msd": "DT.UTR.SIN.IND",
"pos": "DT"
},
{
"word": "grupp",
"deprel": "IO",
"dephead": "18",
"ref": "20",
"lemma": "|grupp|",
"msd": "NN.UTR.SIN.IND.NOM",
"pos": "NN"
},
{
"word": "motsvarande",
"deprel": "DT",
"dephead": "23",
"ref": "21",
"lemma": "|motsvara|motsvarande|",
"msd": "PC.PRS.UTR+NEU.SIN+PLU.IND+DEF.NOM",
"pos": "PC"
},
{
"word": "en",
"deprel": "DT",
"dephead": "23",
"ref": "22",
"lemma": "|en|",
"msd": "DT.UTR.SIN.IND",
"pos": "DT"
},
{
"word": "fj\u00e4rdedels",
"deprel": "DT",
"dephead": "24",
"ref": "23",
"lemma": "|fj\u00e4rdedel|",
"msd": "NN.UTR.SIN.IND.GEN",
"pos": "NN"
},
{
"word": "procent",
"deprel": "OO",
"dephead": "18",
"ref": "24",
"lemma": "|procent|",
"msd": "NN.UTR.PLU.IND.NOM",
"pos": "NN"
},
{
"word": "av",
"deprel": "ET",
"dephead": "24",
"ref": "25",
"lemma": "|av|",
"msd": "PP",
"pos": "PP"
},
{
"word": "Sveriges",
"deprel": "DT",
"dephead": "27",
"ref": "26",
"lemma": "|Sverige|",
"msd": "PM.GEN",
"pos": "PM"
},
{
"word": "befolkning",
"deprel": "PA",
"dephead": "25",
"ref": "27",
"lemma": "|befolkning|",
"msd": "NN.UTR.SIN.IND.NOM",
"pos": "NN"
},
{
"word": "kommer",
"deprel": "MS",
"dephead": "2",
"ref": "28",
"lemma": "|komma|",
"msd": "VB.PRS.AKT",
"pos": "VB"
},
{
"word": "\u00e5tminstone",
"deprel": "MA",
"dephead": "28",
"ref": "29",
"lemma": "|\u00e5tminstone|",
"msd": "AB",
"pos": "AB"
},
{
"word": "jag",
"deprel": "SS",
"dephead": "28",
"ref": "30",
"lemma": "|jag|",
"msd": "PN.UTR.SIN.DEF.SUB",
"pos": "PN"
},
{
"word": "att",
"deprel": "VG",
"dephead": "28",
"ref": "31",
"lemma": "|att|",
"msd": "IE",
"pos": "IE"
},
{
"word": "bli",
"deprel": "IF",
"dephead": "31",
"ref": "32",
"lemma": "|bli|",
"msd": "VB.INF.AKT",
"pos": "VB"
},
{
"word": "provocerad",
"deprel": "SP",
"dephead": "32",
"ref": "33",
"lemma": "|provocera|",
"msd": "PC.PRF.UTR.SIN.IND.NOM",
"pos": "PC"
},
{
"word": ".",
"deprel": "IP",
"dephead": "2",
"ref": "34",
"lemma": "|",
"msd": "MAD",
"pos": "MAD"
}
]
},
{
"corpus": "DA",
"match": {
"position": 357053,
"start": 27,
"end": 32
},
"structs": {
"text_date": "2010-05-26 15:13:04",
"text_id": "7038",
"text_author": "Magnus \u00c5sblad"
},
"tokens": [
{
"word": "Det",
"deprel": "PA",
"dephead": "8",
"ref": "1",
"lemma": "|den|",
"msd": "PN.NEU.SIN.DEF.SUB+OBJ",
"pos": "PN"
},
{
"word": "kan",
"deprel": "ROOT",
"dephead": null,
"ref": "2",
"lemma": "|kunna|",
"msd": "VB.PRS.AKT",
"pos": "VB"
},
{
"word": "man",
"deprel": "SS",
"dephead": "2",
"ref": "3",
"lemma": "|man|",
"msd": "PN.UTR.SIN.IND.SUB",
"pos": "PN"
},
{
"word": "tycka",
"deprel": "VG",
"dephead": "2",
"ref": "4",
"lemma": "|tycka|",
"msd": "VB.INF.AKT",
"pos": "VB"
},
{
"word": "vad",
"deprel": "PA",
"dephead": "8",
"ref": "5",
"lemma": "|vad|",
"msd": "HP.NEU.SIN.IND",
"pos": "HP"
},
{
"word": "man",
"deprel": "SS",
"dephead": "7",
"ref": "6",
"lemma": "|man|",
"msd": "PN.UTR.SIN.IND.SUB",
"pos": "PN"
},
{
"word": "vill",
"deprel": "OO",
"dephead": "4",
"ref": "7",
"lemma": "|vilja|",
"msd": "VB.PRS.AKT",
"pos": "VB"
},
{
"word": "om",
"deprel": "OA",
"dephead": "7",
"ref": "8",
"lemma": "|om|",
"msd": "PP",
"pos": "PP"
},
{
"word": "\u2013",
"deprel": "PA",
"dephead": "8",
"ref": "9",
"lemma": "|",
"msd": "MID",
"pos": "MID"
},
{
"word": "men",
"deprel": "OO",
"dephead": "4",
"ref": "10",
"lemma": "|men|",
"msd": "KN",
"pos": "KN"
},
{
"word": "om",
"deprel": "CJ",
"dephead": "10",
"ref": "11",
"lemma": "|om|",
"msd": "SN",
"pos": "SN"
},
{
"word": "riksdagsvalet",
"deprel": "SS",
"dephead": "13",
"ref": "12",
"lemma": "|riksdagsval|",
"msd": "NN.NEU.SIN.DEF.NOM",
"pos": "NN"
},
{
"word": "kommer",
"deprel": "UA",
"dephead": "11",
"ref": "13",
"lemma": "|komma|",
"msd": "VB.PRS.AKT",
"pos": "VB"
},
{
"word": "att",
"deprel": "VG",
"dephead": "13",
"ref": "14",
"lemma": "|att|",
"msd": "IE",
"pos": "IE"
},
{
"word": "handlar",
"deprel": "IF",
"dephead": "14",
"ref": "15",
"lemma": "|handla|",
"msd": "VB.PRS.AKT",
"pos": "VB"
},
{
"word": "om",
"deprel": "OA",
"dephead": "15",
"ref": "16",
"lemma": "|om|",
"msd": "PP",
"pos": "PP"
},
{
"word": "att",
"deprel": "PA",
"dephead": "16",
"ref": "17",
"lemma": "|att|",
"msd": "IE",
"pos": "IE"
},
{
"word": "blidka",
"deprel": "IF",
"dephead": "17",
"ref": "18",
"lemma": "|blidka|",
"msd": "VB.INF.AKT",
"pos": "VB"
},
{
"word": "en",
"deprel": "DT",
"dephead": "20",
"ref": "19",
"lemma": "|en|",
"msd": "DT.UTR.SIN.IND",
"pos": "DT"
},
{
"word": "grupp",
"deprel": "IO",
"dephead": "18",
"ref": "20",
"lemma": "|grupp|",
"msd": "NN.UTR.SIN.IND.NOM",
"pos": "NN"
},
{
"word": "motsvarande",
"deprel": "DT",
"dephead": "23",
"ref": "21",
"lemma": "|motsvara|motsvarande|",
"msd": "PC.PRS.UTR+NEU.SIN+PLU.IND+DEF.NOM",
"pos": "PC"
},
{
"word": "en",
"deprel": "DT",
"dephead": "23",
"ref": "22",
"lemma": "|en|",
"msd": "DT.UTR.SIN.IND",
"pos": "DT"
},
{
"word": "fj\u00e4rdedels",
"deprel": "DT",
"dephead": "24",
"ref": "23",
"lemma": "|fj\u00e4rdedel|",
"msd": "NN.UTR.SIN.IND.GEN",
"pos": "NN"
},
{
"word": "procent",
"deprel": "OO",
"dephead": "18",
"ref": "24",
"lemma": "|procent|",
"msd": "NN.UTR.PLU.IND.NOM",
"pos": "NN"
},
{
"word": "av",
"deprel": "ET",
"dephead": "24",
"ref": "25",
"lemma": "|av|",
"msd": "PP",
"pos": "PP"
},
{
"word": "Sveriges",
"deprel": "DT",
"dephead": "27",
"ref": "26",
"lemma": "|Sverige|",
"msd": "PM.GEN",
"pos": "PM"
},
{
"word": "befolkning",
"deprel": "PA",
"dephead": "25",
"ref": "27",
"lemma": "|befolkning|",
"msd": "NN.UTR.SIN.IND.NOM",
"pos": "NN"
},
{
"word": "kommer",
"deprel": "MS",
"dephead": "2",
"ref": "28",
"lemma": "|komma|",
"msd": "VB.PRS.AKT",
"pos": "VB"
},
{
"word": "\u00e5tminstone",
"deprel": "MA",
"dephead": "28",
"ref": "29",
"lemma": "|\u00e5tminstone|",
"msd": "AB",
"pos": "AB"
},
{
"word": "jag",
"deprel": "SS",
"dephead": "28",
"ref": "30",
"lemma": "|jag|",
"msd": "PN.UTR.SIN.DEF.SUB",
"pos": "PN"
},
{
"word": "att",
"deprel": "VG",
"dephead": "28",
"ref": "31",
"lemma": "|att|",
"msd": "IE",
"pos": "IE"
},
{
"word": "bli",
"deprel": "IF",
"dephead": "31",
"ref": "32",
"lemma": "|bli|",
"msd": "VB.INF.AKT",
"pos": "VB"
},
{
"word": "provocerad",
"deprel": "SP",
"dephead": "32",
"ref": "33",
"lemma": "|provocera|",
"msd": "PC.PRF.UTR.SIN.IND.NOM",
"pos": "PC"
},
{
"word": ".",
"deprel": "IP",
"dephead": "2",
"ref": "34",
"lemma": "|",
"msd": "MAD",
"pos": "MAD"
}
]
},
{
"corpus": "DA",
"match": {
"position": 368379,
"start": 7,
"end": 10
},
"structs": {
"text_date": "2010-05-03 11:01:29",
"text_id": "editorial-a-kassan-samst-i-oecd",
"text_author": "Mikael F\u00e4rnbo"
},
"tokens": [
{
"word": "Fyra",
"deprel": "DT",
"dephead": "2",
"ref": "1",
"lemma": "|fyra|",
"msd": "RG.NOM",
"pos": "RG"
},
{
"word": "\u00e5r",
"deprel": "TA",
"dephead": "8",
"ref": "2",
"lemma": "|\u00e5r|",
"msd": "NN.NEU.PLU.IND.NOM",
"pos": "NN"
},
{
"word": "till",
"deprel": "ET",
"dephead": "2",
"ref": "3",
"lemma": "|till|",
"msd": "AB",
"pos": "AB"
},
{
"word": "med",
"deprel": "ET",
"dephead": "2",
"ref": "4",
"lemma": "|med|",
"msd": "PP",
"pos": "PP"
},
{
"word": "Reinfeldt",
"deprel": "CJ",
"dephead": "6",
"ref": "5",
"lemma": "|Reinfeldt|",
"msd": "PM.NOM",
"pos": "PM"
},
{
"word": "och",
"deprel": "PA",
"dephead": "4",
"ref": "6",
"lemma": "|och|",
"msd": "KN",
"pos": "KN"
},
{
"word": "bild\u00e4cken",
"deprel": "CJ",
"dephead": "6",
"ref": "7",
"lemma": "|bild\u00e4ck|",
"msd": "NN.UTR.SIN.DEF.NOM",
"pos": "NN"
},
{
"word": "kommer",
"deprel": "ROOT",
"dephead": null,
"ref": "8",
"lemma": "|komma|",
"msd": "VB.PRS.AKT",
"pos": "VB"
},
{
"word": "att",
"deprel": "VG",
"dephead": "8",
"ref": "9",
"lemma": "|att|",
"msd": "IE",
"pos": "IE"
},
{
"word": "brinna",
"deprel": "IF",
"dephead": "9",
"ref": "10",
"lemma": "|brinna|",
"msd": "VB.INF.AKT",
"pos": "VB"
},
{
"word": "\u00e4ven",
"deprel": "+A",
"dephead": "10",
"ref": "11",
"lemma": "|\u00e4ven|",
"msd": "AB",
"pos": "AB"
},
{
"word": "i",
"deprel": "RA",
"dephead": "10",
"ref": "12",
"lemma": "|i|",
"msd": "PP",
"pos": "PP"
},
{
"word": "Sverige",
"deprel": "PA",
"dephead": "12",
"ref": "13",
"lemma": "|Sverige|",
"msd": "PM.NOM",
"pos": "PM"
},
{
"word": ".",
"deprel": "IP",
"dephead": "8",
"ref": "14",
"lemma": "|",
"msd": "MAD",
"pos": "MAD"
}
]
},
{
"corpus": "DA",
"match": {
"position": 368909,
"start": 4,
"end": 11
},
"structs": {
"text_date": "2010-05-05 16:38:12",
"text_id": "editorial-dyr-affar-for-stockholmarna",
"text_author": "Yonna Waltersson"
},
"tokens": [
{
"word": "Enligt",
"deprel": "AA",
"dephead": "5",
"ref": "1",
"lemma": "|enligt|",
"msd": "PP",
"pos": "PP"
},
{
"word": "den",
"deprel": "DT",
"dephead": "4",
"ref": "2",
"lemma": "|den|en|",
"msd": "DT.UTR.SIN.DEF",
"pos": "DT"
},
{
"word": "borgerliga",
"deprel": "AT",
"dephead": "4",
"ref": "3",
"lemma": "|borgerlig|",
"msd": "JJ.POS.UTR+NEU.SIN.DEF.NOM",
"pos": "JJ"
},
{
"word": "majoriteten",
"deprel": "PA",
"dephead": "1",
"ref": "4",
"lemma": "|majoritet|",
"msd": "NN.UTR.SIN.DEF.NOM",
"pos": "NN"
},
{
"word": "kommer",
"deprel": "ROOT",
"dephead": null,
"ref": "5",
"lemma": "|komma|",
"msd": "VB.PRS.AKT",
"pos": "VB"
},
{
"word": "bygget",
"deprel": "SS",
"dephead": "5",
"ref": "6",
"lemma": "|bygge|",
"msd": "NN.NEU.SIN.DEF.NOM",
"pos": "NN"
},
{
"word": "av",
"deprel": "ET",
"dephead": "6",
"ref": "7",
"lemma": "|av|",
"msd": "PP",
"pos": "PP"
},
{
"word": "sj\u00e4lva",
"deprel": "DT",
"dephead": "9",
"ref": "8",
"lemma": "|sj\u00e4lv|sj\u00e4lva|",
"msd": "JJ.POS.UTR+NEU.SIN.DEF.NOM",
"pos": "JJ"
},
{
"word": "sjukhuset",
"deprel": "PA",
"dephead": "7",
"ref": "9",
"lemma": "|sjukhus|",
"msd": "NN.NEU.SIN.DEF.NOM",
"pos": "NN"
},
{
"word": "att",
"deprel": "VG",
"dephead": "5",
"ref": "10",
"lemma": "|att|",
"msd": "IE",
"pos": "IE"
},
{
"word": "kosta",
"deprel": "IF",
"dephead": "10",
"ref": "11",
"lemma": "|kosta|",
"msd": "VB.INF.AKT",
"pos": "VB"
},
{
"word": "14,5",
"deprel": "DT",
"dephead": "13",
"ref": "12",
"lemma": "|",
"msd": "RG.NOM",
"pos": "RG"
},
{
"word": "miljarder",
"deprel": "DT",
"dephead": "14",
"ref": "13",
"lemma": "|miljard|",
"msd": "NN.UTR.PLU.IND.NOM",
"pos": "NN"
},
{
"word": "kronor",
"deprel": "OO",
"dephead": "11",
"ref": "14",
"lemma": "|krona|",
"msd": "NN.UTR.PLU.IND.NOM",
"pos": "NN"
},
{
"word": ".",
"deprel": "IP",
"dephead": "5",
"ref": "15",
"lemma": "|",
"msd": "MAD",
"pos": "MAD"
}
]
},
{
"corpus": "DA",
"match": {
"position": 368925,
"start": 5,
"end": 8
},
"structs": {
"text_date": "2010-05-05 16:38:12",
"text_id": "editorial-dyr-affar-for-stockholmarna",
"text_author": "Yonna Waltersson"
},
"tokens": [
{
"word": "Oppositionen",
"deprel": "SS",
"dephead": "2",
"ref": "1",
"lemma": "|opposition|",
"msd": "NN.UTR.SIN.DEF.NOM",
"pos": "NN"
},
{
"word": "p\u00e5pekar",
"deprel": "ROOT",
"dephead": null,
"ref": "2",
"lemma": "|p\u00e5peka|",
"msd": "VB.PRS.AKT",
"pos": "VB"
},
{
"word": "att",
"deprel": "OO",
"dephead": "2",
"ref": "3",
"lemma": "|att|",
"msd": "SN",
"pos": "SN"
},
{
"word": "slutsiffran",
"deprel": "SS",
"dephead": "6",
"ref": "4",
"lemma": "|slutsiffra|",
"msd": "NN.UTR.SIN.DEF.NOM",
"pos": "NN"
},
{
"word": "snarare",
"deprel": "AA",
"dephead": "6",
"ref": "5",
"lemma": "|snar|snarare|",
"msd": "AB.KOM",
"pos": "AB"
},
{
"word": "kommer",
"deprel": "UA",
"dephead": "3",
"ref": "6",
"lemma": "|komma|",
"msd": "VB.PRS.AKT",
"pos": "VB"
},
{
"word": "att",
"deprel": "VG",
"dephead": "6",
"ref": "7",
"lemma": "|att|",
"msd": "IE",
"pos": "IE"
},
{
"word": "hamna",
"deprel": "IF",
"dephead": "7",
"ref": "8",
"lemma": "|hamna|",
"msd": "VB.INF.AKT",
"pos": "VB"
},
{
"word": "p\u00e5",
"deprel": "OA",
"dephead": "8",
"ref": "9",
"lemma": "|p\u00e5|",
"msd": "PP",
"pos": "PP"
},
{
"word": "22",
"deprel": "DT",
"dephead": "11",
"ref": "10",
"lemma": "|",
"msd": "RG.NOM",
"pos": "RG"
},
{
"word": "miljarder",
"deprel": "DT",
"dephead": "12",
"ref": "11",
"lemma": "|miljard|",
"msd": "NN.UTR.PLU.IND.NOM",
"pos": "NN"
},
{
"word": "kronor",
"deprel": "PA",
"dephead": "9",
"ref": "12",
"lemma": "|krona|",
"msd": "NN.UTR.PLU.IND.NOM",
"pos": "NN"
},
{
"word": ".",
"deprel": "IP",
"dephead": "2",
"ref": "13",
"lemma": "|",
"msd": "MAD",
"pos": "MAD"
}
]
},
{
"corpus": "DA",
"match": {
"position": 369520,
"start": 19,
"end": 22
},
"structs": {
"text_date": "2010-05-26 09:47:02",
"text_id": "7017",
"text_author": "Magnus \u00c5sblad"
},
"tokens": [
{
"word": "Hade",
"deprel": "ROOT",
"dephead": null,
"ref": "1",
"lemma": "|ha|",
"msd": "VB.PRT.AKT",
"pos": "VB"
},
{
"word": "det",
"deprel": "SS",
"dephead": "1",
"ref": "2",
"lemma": "|den|",
"msd": "PN.NEU.SIN.DEF.SUB+OBJ",
"pos": "PN"
},
{
"word": "varit",
"deprel": "VG",
"dephead": "1",
"ref": "3",
"lemma": "|vara|",
"msd": "VB.SUP.AKT",
"pos": "VB"
},
{
"word": "mer",
"deprel": "AA",
"dephead": "5",
"ref": "4",
"lemma": "|mer|mycket|",
"msd": "AB.KOM",
"pos": "AB"
},
{
"word": "riktigt",
"deprel": "CJ",
"dephead": "7",
"ref": "5",
"lemma": "|riktig|",
"msd": "AB",
"pos": "AB"
},
{
"word": "\u2013",
"deprel": "CJ",
"dephead": "7",
"ref": "6",
"lemma": "|",
"msd": "JJ.KOM.UTR+NEU.SIN+PLU.IND+DEF.NOM",
"pos": "JJ"
},
{
"word": "och",
"deprel": "SP",
"dephead": "3",
"ref": "7",
"lemma": "|och|",
"msd": "KN",
"pos": "KN"
},
{
"word": "mer",
"deprel": "CJ",
"dephead": "7",
"ref": "8",
"lemma": "|mer|mycket|",
"msd": "AB.KOM",
"pos": "AB"
},
{
"word": "i",
"deprel": "CJ",
"dephead": "7",
"ref": "9",
"lemma": "|i|i_samklang|",
"msd": "PP",
"pos": "PP"
},
{
"word": "samklang",
"deprel": "HD",
"dephead": "9",
"ref": "10",
"lemma": "|samklang|i_samklang:9|",
"msd": "NN.UTR.SIN.IND.NOM",
"pos": "NN"
},
{
"word": "med",
"deprel": "HD",
"dephead": "9",
"ref": "11",
"lemma": "|med|",
"msd": "PP",
"pos": "PP"
},
{
"word": "den",
"deprel": "DT",
"dephead": "14",
"ref": "12",
"lemma": "|den|en|",
"msd": "DT.UTR.SIN.DEF",
"pos": "DT"
},
{
"word": "faktiska",
"deprel": "AT",
"dephead": "14",
"ref": "13",
"lemma": "|faktisk|",
"msd": "JJ.POS.UTR+NEU.SIN.DEF.NOM",
"pos": "JJ"
},
{
"word": "utrikespolitik",
"deprel": "PA",
"dephead": "9",
"ref": "14",
"lemma": "|utrikespolitik|",
"msd": "NN.UTR.SIN.IND.NOM",
"pos": "NN"
},
{
"word": "som",
"deprel": "OO",
"dephead": "22",
"ref": "15",
"lemma": "|",
"msd": "HP.-.-.-",
"pos": "HP"
},
{
"word": "en",
"deprel": "DT",
"dephead": "18",
"ref": "16",
"lemma": "|en|",
"msd": "DT.UTR.SIN.IND",
"pos": "DT"
},
{
"word": "r\u00f6dgr\u00f6n",
"deprel": "AT",
"dephead": "18",
"ref": "17",
"lemma": "|r\u00f6dgr\u00f6n|",
"msd": "JJ.POS.UTR.SIN.IND.NOM",
"pos": "JJ"
},
{
"word": "regering",
"deprel": "SS",
"dephead": "20",
"ref": "18",
"lemma": "|regering|",
"msd": "NN.UTR.SIN.IND.NOM",
"pos": "NN"
},
{
"word": "f\u00f6rmodligen",
"deprel": "MA",
"dephead": "20",
"ref": "19",
"lemma": "|f\u00f6rmodligen|",
"msd": "AB",
"pos": "AB"
},
{
"word": "kommer",
"deprel": "ET",
"dephead": "14",
"ref": "20",
"lemma": "|komma|",
"msd": "VB.PRS.AKT",
"pos": "VB"
},
{
"word": "att",
"deprel": "VG",
"dephead": "20",
"ref": "21",
"lemma": "|att|",
"msd": "IE",
"pos": "IE"
},
{
"word": "f\u00f6ra",
"deprel": "IF",
"dephead": "21",
"ref": "22",
"lemma": "|f\u00f6ra|",
"msd": "VB.INF.AKT",
"pos": "VB"
},
{
"word": "vid",
"deprel": "OA",
"dephead": "22",
"ref": "23",
"lemma": "|vid|",
"msd": "PP",
"pos": "PP"
},
{
"word": "en",
"deprel": "DT",
"dephead": "26",
"ref": "24",
"lemma": "|en|",
"msd": "DT.UTR.SIN.IND",
"pos": "DT"
},
{
"word": "eventuell",
"deprel": "AT",
"dephead": "26",
"ref": "25",
"lemma": "|eventuell|",
"msd": "JJ.POS.UTR.SIN.IND.NOM",
"pos": "JJ"
},
{
"word": "valvinst",
"deprel": "PA",
"dephead": "23",
"ref": "26",
"lemma": "|valvinst|",
"msd": "NN.UTR.SIN.IND.NOM",
"pos": "NN"
},
{
"word": "i",
"deprel": "TA",
"dephead": "22",
"ref": "27",
"lemma": "|i|",
"msd": "PP",
"pos": "PP"
},
{
"word": "h\u00f6st",
"deprel": "HD",
"dephead": "27",
"ref": "28",
"lemma": "|h\u00f6st|",
"msd": "NN.UTR.SIN.IND.NOM",
"pos": "NN"
},
{
"word": "\u2013",
"deprel": "AA",
"dephead": "22",
"ref": "29",
"lemma": "|",
"msd": "PP",
"pos": "PP"
},
{
"word": "att",
"deprel": "PA",
"dephead": "29",
"ref": "30",
"lemma": "|att|",
"msd": "IE",
"pos": "IE"
},
{
"word": "skriva",
"deprel": "IF",
"dephead": "30",
"ref": "31",
"lemma": "|skriva|",
"msd": "VB.INF.AKT",
"pos": "VB"
},
{
"word": "n\u00e5got",
"deprel": "OO",
"dephead": "31",
"ref": "32",
"lemma": "|n\u00e5gon|",
"msd": "PN.NEU.SIN.IND.SUB+OBJ",
"pos": "PN"
},
{
"word": "i",
"deprel": "AA",
"dephead": "31",
"ref": "33",
"lemma": "|i|",
"msd": "PP",
"pos": "PP"
},
{
"word": "stil",
"deprel": "HD",
"dephead": "33",
"ref": "34",
"lemma": "|stil|",
"msd": "NN.UTR.SIN.IND.NOM",
"pos": "NN"
},
{
"word": "med",
"deprel": "OA",
"dephead": "31",
"ref": "35",
"lemma": "|med|",
"msd": "PP",
"pos": "PP"
},
{
"word": "att",
"deprel": "PA",
"dephead": "35",
"ref": "36",
"lemma": "|att|",
"msd": "SN",
"pos": "SN"
},
{
"word": "\u201d",
"deprel": "DT",
"dephead": "38",
"ref": "37",
"lemma": "|",
"msd": "PAD",
"pos": "PAD"
},
{
"word": "USA",
"deprel": "SS",
"dephead": "39",
"ref": "38",
"lemma": "|USA|",
"msd": "PM.NOM",
"pos": "PM"
},
{
"word": "b\u00f6r",
"deprel": "UA",
"dephead": "36",
"ref": "39",
"lemma": "|b\u00f6ra|",
"msd": "VB.PRS.AKT",
"pos": "VB"
},
{
"word": "leda",
"deprel": "VG",
"dephead": "39",
"ref": "40",
"lemma": "|leda|",
"msd": "VB.INF.AKT",
"pos": "VB"
},
{
"word": "nedrustningen",
"deprel": "OO",
"dephead": "40",
"ref": "41",
"lemma": "|nedrustning|",
"msd": "NN.UTR.SIN.DEF.NOM",
"pos": "NN"
},
{
"word": "i",
"deprel": "ET",
"dephead": "41",
"ref": "42",
"lemma": "|i|",
"msd": "PP",
"pos": "PP"
},
{
"word": "v\u00e4rlden",
"deprel": "PA",
"dephead": "42",
"ref": "43",
"lemma": "|v\u00e4rld|",
"msd": "NN.UTR.SIN.DEF.NOM",
"pos": "NN"
},
{
"word": ",",
"deprel": "IK",
"dephead": "45",
"ref": "44",
"lemma": "|",
"msd": "MID",
"pos": "MID"
},
{
"word": "och",
"deprel": "UA",
"dephead": "36",
"ref": "45",
"lemma": "|och|",
"msd": "KN",
"pos": "KN"
},
{
"word": "f\u00f6reg\u00e5",
"deprel": "+F",
"dephead": "45",
"ref": "46",
"lemma": "|f\u00f6reg\u00e5|",
"msd": "VB.INF.AKT",
"pos": "VB"
},
{
"word": "med",
"deprel": "AA",
"dephead": "46",
"ref": "47",
"lemma": "|med|",
"msd": "PP",
"pos": "PP"
},
{
"word": "gott",
"deprel": "AT",
"dephead": "49",
"ref": "48",
"lemma": "|god|gott|",
"msd": "JJ.POS.NEU.SIN.IND.NOM",
"pos": "JJ"
},
{
"word": "exempel",
"deprel": "PA",
"dephead": "47",
"ref": "49",
"lemma": "|exempel|",
"msd": "NN.NEU.SIN.IND.NOM",
"pos": "NN"
},
{
"word": "genom",
"deprel": "AA",
"dephead": "46",
"ref": "50",
"lemma": "|genom|",
"msd": "PP",
"pos": "PP"
},
{
"word": "att",
"deprel": "PA",
"dephead": "50",
"ref": "51",
"lemma": "|att|",
"msd": "IE",
"pos": "IE"
},
{
"word": "b\u00f6rja",
"deprel": "IF",
"dephead": "51",
"ref": "52",
"lemma": "|b\u00f6rja|",
"msd": "VB.INF.AKT",
"pos": "VB"
},
{
"word": "avveckla",
"deprel": "OO",
"dephead": "52",
"ref": "53",
"lemma": "|avveckla|",
"msd": "VB.INF.AKT",
"pos": "VB"
},
{
"word": "sina",
"deprel": "DT",
"dephead": "56",
"ref": "54",
"lemma": "|sig|",
"msd": "PS.UTR+NEU.PLU.DEF",
"pos": "PS"
},
{
"word": "milit\u00e4ra",
"deprel": "AT",
"dephead": "56",
"ref": "55",
"lemma": "|milit\u00e4r|",
"msd": "JJ.POS.UTR+NEU.PLU.IND+DEF.NOM",
"pos": "JJ"
},
{
"word": "baser",
"deprel": "OO",
"dephead": "53",
"ref": "56",
"lemma": "|bas|",
"msd": "NN.UTR.PLU.IND.NOM",
"pos": "NN"
},
{
"word": "utanf\u00f6r",
"deprel": "RA",
"dephead": "53",
"ref": "57",
"lemma": "|utanf\u00f6r|",
"msd": "PP",
"pos": "PP"
},
{
"word": "landets",
"deprel": "DT",
"dephead": "59",
"ref": "58",
"lemma": "|land|",
"msd": "NN.NEU.SIN.DEF.GEN",
"pos": "NN"
},
{
"word": "gr\u00e4nser",
"deprel": "PA",
"dephead": "57",
"ref": "59",
"lemma": "|gr\u00e4ns|",
"msd": "NN.UTR.PLU.IND.NOM",
"pos": "NN"
},
{
"word": "\u201d",
"deprel": "OP",
"dephead": "53",
"ref": "60",
"lemma": "|",
"msd": "PAD",
"pos": "PAD"
},
{
"word": "?",
"deprel": "I?",
"dephead": "1",
"ref": "61",
"lemma": "|",
"msd": "MAD",
"pos": "MAD"
}
]
},
{
"corpus": "DA",
"match": {
"position": 382844,
"start": 1,
"end": 5
},
"structs": {
"text_date": "2010-05-21 11:58:49",
"text_id": "6890",
"text_author": "Yonna Waltersson"
},
"tokens": [
{
"word": "Bonusen",
"deprel": "SS",
"dephead": "2",
"ref": "1",
"lemma": "|bonus|",
"msd": "NN.UTR.SIN.DEF.NOM",
"pos": "NN"
},
{
"word": "kommer",
"deprel": "ROOT",
"dephead": null,
"ref": "2",
"lemma": "|komma|",
"msd": "VB.PRS.AKT",
"pos": "VB"
},
{
"word": "knappast",
"deprel": "NA",
"dephead": "2",
"ref": "3",
"lemma": "|knapp|knappast|",
"msd": "AB.SUV",
"pos": "AB"
},
{
"word": "att",
"deprel": "VG",
"dephead": "2",
"ref": "4",
"lemma": "|att|",
"msd": "IE",
"pos": "IE"
},
{
"word": "n\u00e5",
"deprel": "IF",
"dephead": "4",
"ref": "5",
"lemma": "|n\u00e5|",
"msd": "VB.INF.AKT",
"pos": "VB"
},
{
"word": "dem",
"deprel": "OO",
"dephead": "5",
"ref": "6",
"lemma": "|de|",
"msd": "PN.UTR+NEU.PLU.DEF.OBJ",
"pos": "PN"
},
{
"word": "som",
"deprel": "SS",
"dephead": "9",
"ref": "7",
"lemma": "|som_mest|",
"msd": "HP.-.-.-",
"pos": "HP"
},
{
"word": "mest",
"deprel": "AA",
"dephead": "9",
"ref": "8",
"lemma": "|mycket|som_mest:7|",
"msd": "AB.SUV",
"pos": "AB"
},
{
"word": "skulle",
"deprel": "ET",
"dephead": "6",
"ref": "9",
"lemma": "|skola|",
"msd": "VB.PRT.AKT",
"pos": "VB"
},
{
"word": "beh\u00f6va",
"deprel": "VG",
"dephead": "9",
"ref": "10",
"lemma": "|beh\u00f6va|",
"msd": "VB.INF.AKT",
"pos": "VB"
},
{
"word": "st\u00f6det",
"deprel": "OO",
"dephead": "10",
"ref": "11",
"lemma": "|st\u00f6d|",
"msd": "NN.NEU.SIN.DEF.NOM",
"pos": "NN"
},
{
"word": ".",
"deprel": "IP",
"dephead": "2",
"ref": "12",
"lemma": "|",
"msd": "MAD",
"pos": "MAD"
}
]
},
{
"corpus": "DA",
"match": {
"position": 388182,
"start": 1,
"end": 6
},
"structs": {
"text_date": "2010-05-02 21:39:54",
"text_id": "coverage-inte-sarskilt-realistisk",
"text_author": "H\u00e5kan A Bengtsson"
},
"tokens": [
{
"word": "D\u00e5",
"deprel": "TA",
"dephead": "2",
"ref": "1",
"lemma": "|d\u00e5|",
"msd": "AB",
"pos": "AB"
},
{
"word": "kommer",
"deprel": "ROOT",
"dephead": null,
"ref": "2",
"lemma": "|komma|",
"msd": "VB.PRS.AKT",
"pos": "VB"
},
{
"word": "fler",
"deprel": "SS",
"dephead": "2",
"ref": "3",
"lemma": "|m\u00e5ngen|",
"msd": "PN.UTR+NEU.PLU.IND.SUB+OBJ",
"pos": "PN"
},
{
"word": "att",
"deprel": "VG",
"dephead": "2",
"ref": "4",
"lemma": "|att|",
"msd": "IE",
"pos": "IE"
},
{
"word": "\"",
"deprel": "IF",
"dephead": "4",
"ref": "5",
"lemma": "|",
"msd": "PAD",
"pos": "PAD"
},
{
"word": "ta",
"deprel": "IF",
"dephead": "4",
"ref": "6",
"lemma": "|ta|",
"msd": "VB.INF.AKT",
"pos": "VB"
},
{
"word": "de",
"deprel": "DT",
"dephead": "8",
"ref": "7",
"lemma": "|en|",
"msd": "DT.UTR+NEU.PLU.DEF",
"pos": "DT"
},
{
"word": "jobb",
"deprel": "OO",
"dephead": "6",
"ref": "8",
"lemma": "|jobb|",
"msd": "NN.NEU.PLU.IND.NOM",
"pos": "NN"
},
{
"word": "som",
"deprel": "SS",
"dephead": "11",
"ref": "9",
"lemma": "|",
"msd": "HP.-.-.-",
"pos": "HP"
},
{
"word": "faktiskt",
"deprel": "MA",
"dephead": "11",
"ref": "10",
"lemma": "|faktisk|",
"msd": "AB.POS",
"pos": "AB"
},
{
"word": "finns",
"deprel": "ET",
"dephead": "8",
"ref": "11",
"lemma": "|finna|finnas|",
"msd": "VB.PRS.SFO",
"pos": "VB"
},
{
"word": "\"",
"deprel": "JC",
"dephead": "11",
"ref": "12",
"lemma": "|",
"msd": "PAD",
"pos": "PAD"
},
{
"word": ".",
"deprel": "IP",
"dephead": "2",
"ref": "13",
"lemma": "|",
"msd": "MAD",
"pos": "MAD"
}
]
},
{
"corpus": "DA",
"match": {
"position": 393551,
"start": 7,
"end": 10
},
"structs": {
"text_date": "2010-05-18 18:03:56",
"text_id": "ledare-om-calmfors-och-finanspolitiska-radet",
"text_author": "Nisha Besara"
},
"tokens": [
{
"word": "\u00c4r",
"deprel": "ROOT",
"dephead": null,
"ref": "1",
"lemma": "|vara|",
"msd": "VB.PRS.AKT",
"pos": "VB"
},
{
"word": "det",
"deprel": "SS",
"dephead": "1",
"ref": "2",
"lemma": "|den|",
"msd": "PN.NEU.SIN.DEF.SUB+OBJ",
"pos": "PN"
},
{
"word": "n\u00e5gon",
"deprel": "XX",
"dephead": "1",
"ref": "3",
"lemma": "|n\u00e5gon|",
"msd": "PN.UTR.SIN.IND.SUB+OBJ",
"pos": "PN"
},
{
"word": "som",
"deprel": "SS",
"dephead": "5",
"ref": "4",
"lemma": "|",
"msd": "HP.-.-.-",
"pos": "HP"
},
{
"word": "tror",
"deprel": "EF",
"dephead": "3",
"ref": "5",
"lemma": "|tro|",
"msd": "VB.PRS.AKT",
"pos": "VB"
},
{
"word": "att",
"deprel": "OO",
"dephead": "5",
"ref": "6",
"lemma": "|att|",
"msd": "SN",
"pos": "SN"
},
{
"word": "Calmfors",
"deprel": "SS",
"dephead": "8",
"ref": "7",
"lemma": "|",
"msd": "PM.NOM",
"pos": "PM"
},
{
"word": "kommer",
"deprel": "UA",
"dephead": "6",
"ref": "8",
"lemma": "|komma|",
"msd": "VB.PRS.AKT",
"pos": "VB"
},
{
"word": "att",
"deprel": "VG",
"dephead": "8",
"ref": "9",
"lemma": "|att|",
"msd": "IE",
"pos": "IE"
},
{
"word": "r\u00f6sta",
"deprel": "IF",
"dephead": "9",
"ref": "10",
"lemma": "|r\u00f6sta|",
"msd": "VB.INF.AKT",
"pos": "VB"
},
{
"word": "p\u00e5",
"deprel": "OA",
"dephead": "10",
"ref": "11",
"lemma": "|p\u00e5|",
"msd": "PP",
"pos": "PP"
},
{
"word": "den",
"deprel": "DT",
"dephead": "14",
"ref": "12",
"lemma": "|den|en|",
"msd": "DT.UTR.SIN.DEF",
"pos": "DT"
},
{
"word": "r\u00f6dgr\u00f6na",
"deprel": "AT",
"dephead": "14",
"ref": "13",
"lemma": "|r\u00f6dgr\u00f6n|",
"msd": "JJ.POS.UTR+NEU.SIN.DEF.NOM",
"pos": "JJ"
},
{
"word": "oppositionen",
"deprel": "PA",
"dephead": "11",
"ref": "14",
"lemma": "|opposition|",
"msd": "NN.UTR.SIN.DEF.NOM",
"pos": "NN"
},
{
"word": "den",
"deprel": "DT",
"dephead": "17",
"ref": "15",
"lemma": "|den|en|",
"msd": "DT.UTR.SIN.DEF",
"pos": "DT"
},
{
"word": "19",
"deprel": "DT",
"dephead": "17",
"ref": "16",
"lemma": "|",
"msd": "RG.NOM",
"pos": "RG"
},
{
"word": "september",
"deprel": "ET",
"dephead": "14",
"ref": "17",
"lemma": "|september|",
"msd": "NN.UTR.SIN.IND.NOM",
"pos": "NN"
},
{
"word": "?",
"deprel": "I?",
"dephead": "1",
"ref": "18",
"lemma": "|",
"msd": "MAD",
"pos": "MAD"
}
]
},
{
"corpus": "DA",
"match": {
"position": 404757,
"start": 6,
"end": 9
},
"structs": {
"text_date": "2010-05-07 00:18:48",
"text_id": "coverage-nick-clegg-bestammer",
"text_author": "H\u00e5kan A Bengtsson"
},
"tokens": [
{
"word": "Men",
"deprel": "ROOT",
"dephead": null,
"ref": "1",
"lemma": "|men|",
"msd": "KN",
"pos": "KN"
},
{
"word": "har",
"deprel": "MS",
"dephead": "6",
"ref": "2",
"lemma": "|ha|",
"msd": "VB.PRS.AKT",
"pos": "VB"
},
{
"word": "ingen",
"deprel": "DT",
"dephead": "5",
"ref": "3",
"lemma": "|ingen|",
"msd": "DT.UTR.SIN.IND",
"pos": "DT"
},
{
"word": "egen",
"deprel": "DT",
"dephead": "5",
"ref": "4",
"lemma": "|egen|",
"msd": "JJ.POS.UTR.SIN.IND+DEF.NOM",
"pos": "JJ"
},
{
"word": "majoritet",
"deprel": "OO",
"dephead": "2",
"ref": "5",
"lemma": "|majoritet|",
"msd": "NN.UTR.SIN.IND.NOM",
"pos": "NN"
},
{
"word": "och",
"deprel": "++",
"dephead": "1",
"ref": "6",
"lemma": "|och|",
"msd": "KN",
"pos": "KN"
},
{
"word": "kommer",
"deprel": "+F",
"dephead": "6",
"ref": "7",
"lemma": "|komma|",
"msd": "VB.PRS.AKT",
"pos": "VB"
},
{
"word": "att",
"deprel": "VG",
"dephead": "7",
"ref": "8",
"lemma": "|att|",
"msd": "IE",
"pos": "IE"
},
{
"word": "beh\u00f6va",
"deprel": "IF",
"dephead": "8",
"ref": "9",
"lemma": "|beh\u00f6va|",
"msd": "VB.INF.AKT",
"pos": "VB"
},
{
"word": "kohandla",
"deprel": "VG",
"dephead": "9",
"ref": "10",
"lemma": "|kohandla|",
"msd": "VB.INF.AKT",
"pos": "VB"
},
{
"word": "med",
"deprel": "OA",
"dephead": "10",
"ref": "11",
"lemma": "|med|",
"msd": "PP",
"pos": "PP"
},
{
"word": "n\u00e5got",
"deprel": "PA",
"dephead": "11",
"ref": "12",
"lemma": "|n\u00e5gon|",
"msd": "PN.NEU.SIN.IND.SUB+OBJ",
"pos": "PN"
},
{
"word": "av",
"deprel": "ET",
"dephead": "12",
"ref": "13",
"lemma": "|av|",
"msd": "PP",
"pos": "PP"
},
{
"word": "de",
"deprel": "DT",
"dephead": "16",
"ref": "14",
"lemma": "|en|",
"msd": "DT.UTR+NEU.PLU.DEF",
"pos": "DT"
},
{
"word": "andra",
"deprel": "DT",
"dephead": "16",
"ref": "15",
"lemma": "|andra|annan|",
"msd": "JJ.POS.UTR+NEU.PLU.IND+DEF.NOM",
"pos": "JJ"
},
{
"word": "partierna",
"deprel": "PA",
"dephead": "13",
"ref": "16",
"lemma": "|parti|",
"msd": "NN.NEU.PLU.DEF.NOM",
"pos": "NN"
},
{
"word": ".",
"deprel": "IP",
"dephead": "6",
"ref": "17",
"lemma": "|",
"msd": "MAD",
"pos": "MAD"
}
]
},
{
"corpus": "DA",
"match": {
"position": 426282,
"start": 1,
"end": 8
},
"structs": {
"text_date": "2010-05-26 09:47:02",
"text_id": "7017",
"text_author": "Magnus \u00c5sblad"
},
"tokens": [
{
"word": "Hur",
"deprel": "AA",
"dephead": "2",
"ref": "1",
"lemma": "|hur|",
"msd": "HA",
"pos": "HA"
},
{
"word": "kommer",
"deprel": "ROOT",
"dephead": null,
"ref": "2",
"lemma": "|komma|komma_sig|",
"msd": "VB.PRS.AKT",
"pos": "VB"
},
{
"word": "det",
"deprel": "FS",
"dephead": "2",
"ref": "3",
"lemma": "|den|",
"msd": "PN.NEU.SIN.DEF.SUB+OBJ",
"pos": "PN"
},
{
"word": "sig",
"deprel": "OO",
"dephead": "2",
"ref": "4",
"lemma": "|sig|komma_sig:2|",
"msd": "PN.UTR+NEU.SIN+PLU.DEF.OBJ",
"pos": "PN"
},
{
"word": "att",
"deprel": "ES",
"dephead": "2",
"ref": "5",
"lemma": "|att|",
"msd": "SN",
"pos": "SN"
},
{
"word": "han",
"deprel": "SS",
"dephead": "7",
"ref": "6",
"lemma": "|han|",
"msd": "PN.UTR.SIN.DEF.SUB",
"pos": "PN"
},
{
"word": "f\u00e5r",
"deprel": "UA",
"dephead": "5",
"ref": "7",
"lemma": "|f\u00e5|",
"msd": "VB.PRS.AKT",
"pos": "VB"
},
{
"word": "skriva",
"deprel": "VG",
"dephead": "7",
"ref": "8",
"lemma": "|skriva|",
"msd": "VB.INF.AKT",
"pos": "VB"
},
{
"word": "p\u00e5",
"deprel": "OA",
"dephead": "8",
"ref": "9",
"lemma": "|p\u00e5|",
"msd": "PP",
"pos": "PP"
},
{
"word": "nyhetsplats",
"deprel": "PA",
"dephead": "9",
"ref": "10",
"lemma": "|nyhetsplats|",
"msd": "NN.UTR.SIN.IND.NOM",
"pos": "NN"
},
{
"word": ",",
"deprel": "IK",
"dephead": "10",
"ref": "11",
"lemma": "|",
"msd": "MID",
"pos": "MID"
},
{
"word": "d\u00e4r",
"deprel": "RA",
"dephead": "15",
"ref": "12",
"lemma": "|d\u00e4r|",
"msd": "HA",
"pos": "HA"
},
{
"word": "hans",
"deprel": "DT",
"dephead": "14",
"ref": "13",
"lemma": "|han|",
"msd": "PS.UTR+NEU.SIN+PLU.DEF",
"pos": "PS"
},
{
"word": "analyser",
"deprel": "SS",
"dephead": "15",
"ref": "14",
"lemma": "|analys|",
"msd": "NN.UTR.PLU.IND.NOM",
"pos": "NN"
},
{
"word": "har",
"deprel": "ET",
"dephead": "10",
"ref": "15",
"lemma": "|ha|",
"msd": "VB.PRS.AKT",
"pos": "VB"
},
{
"word": "rubriker",
"deprel": "OO",
"dephead": "15",
"ref": "16",
"lemma": "|rubrik|",
"msd": "NN.UTR.PLU.IND.NOM",
"pos": "NN"
},
{
"word": "som",
"deprel": "PA",
"dephead": "23",
"ref": "17",
"lemma": "|",
"msd": "HP.-.-.-",
"pos": "HP"
},
{
"word": "\u201d",
"deprel": "DT",
"dephead": "19",
"ref": "18",
"lemma": "|",
"msd": "PAD",
"pos": "PAD"
},
{
"word": "S-ledningen",
"deprel": "SS",
"dephead": "20",
"ref": "19",
"lemma": "|s-ledning|",
"msd": "NN.UTR.SIN.DEF.NOM",
"pos": "NN"
},
{
"word": "har",
"deprel": "ET",
"dephead": "16",
"ref": "20",
"lemma": "|ha|",
"msd": "VB.PRS.AKT",
"pos": "VB"
},
{
"word": "tappat",
"deprel": "VG",
"dephead": "20",
"ref": "21",
"lemma": "|tappa|",
"msd": "VB.SUP.AKT",
"pos": "VB"
},
{
"word": "greppet",
"deprel": "OO",
"dephead": "21",
"ref": "22",
"lemma": "|grepp|",
"msd": "NN.NEU.SIN.DEF.NOM",
"pos": "NN"
},
{
"word": "\u201d",
"deprel": "OA",
"dephead": "21",
"ref": "23",
"lemma": "|",
"msd": "MID",
"pos": "MID"
},
{
"word": "?",
"deprel": "I?",
"dephead": "2",
"ref": "24",
"lemma": "|",
"msd": "MAD",
"pos": "MAD"
}
]
},
{
"corpus": "DA",
"match": {
"position": 442106,
"start": 10,
"end": 13
},
"structs": {
"text_date": "2010-05-19 12:41:52",
"text_id": "reportage-mp-har-gjort-ett-val-samarbetet-ar-logiskt",
"text_author": "H\u00e5kan A Bengtsson"
},
"tokens": [
{
"word": "Som",
"deprel": "AA",
"dephead": "6",
"ref": "1",
"lemma": "|",
"msd": "KN",
"pos": "KN"
},
{
"word": "en",
"deprel": "DT",
"dephead": "5",
"ref": "2",
"lemma": "|en|",
"msd": "DT.UTR.SIN.IND",
"pos": "DT"
},
{
"word": "besviken",
"deprel": "AT",
"dephead": "5",
"ref": "3",
"lemma": "|besviken|",
"msd": "JJ.POS.UTR.SIN.IND.NOM",
"pos": "JJ"
},
{
"word": "liberaldemokratisk",
"deprel": "AT",
"dephead": "5",
"ref": "4",
"lemma": "|liberaldemokratisk|",
"msd": "JJ.POS.UTR.SIN.IND.NOM",
"pos": "JJ"
},
{
"word": "bloggare",
"deprel": "UA",
"dephead": "1",
"ref": "5",
"lemma": "|bloggare|",
"msd": "NN.UTR.SIN.IND.NOM",
"pos": "NN"
},
{
"word": "uttryckte",
"deprel": "MS",
"dephead": "20",
"ref": "6",
"lemma": "|uttrycka|",
"msd": "VB.PRT.AKT",
"pos": "VB"
},
{
"word": "det",
"deprel": "SS",
"dephead": "6",
"ref": "7",
"lemma": "|den|",
"msd": "PN.NEU.SIN.DEF.SUB+OBJ",
"pos": "PN"
},
{
"word": ":",
"deprel": "IQ",
"dephead": "6",
"ref": "8",
"lemma": "|",
"msd": "MID",
"pos": "MID"
},
{
"word": "\u201c",
"deprel": "SS",
"dephead": "11",
"ref": "9",
"lemma": "|",
"msd": "NN.UTR.SIN.IND.NOM",
"pos": "NN"
},
{
"word": "Jag",
"deprel": "SS",
"dephead": "11",
"ref": "10",
"lemma": "|jag|",
"msd": "PN.UTR.SIN.DEF.SUB",
"pos": "PN"
},
{
"word": "kommer",
"deprel": "MS",
"dephead": "20",
"ref": "11",
"lemma": "|komma|",
"msd": "VB.PRS.AKT",
"pos": "VB"
},
{
"word": "fullst\u00e4ndigt",
"deprel": "AA",
"dephead": "11",
"ref": "12",
"lemma": "|fullst\u00e4ndig|",
"msd": "AB.POS",
"pos": "AB"
},
{
"word": "hata",
"deprel": "VG",
"dephead": "11",
"ref": "13",
"lemma": "|hata|",
"msd": "VB.INF.AKT",
"pos": "VB"
},
{
"word": "den",
"deprel": "DT",
"dephead": "15",
"ref": "14",
"lemma": "|den|en|",
"msd": "DT.UTR.SIN.DEF",
"pos": "DT"
},
{
"word": "dag",
"deprel": "OO",
"dephead": "13",
"ref": "15",
"lemma": "|dag|",
"msd": "NN.UTR.SIN.IND.NOM",
"pos": "NN"
},
{
"word": "jag",
"deprel": "SS",
"dephead": "17",
"ref": "16",
"lemma": "|jag|",
"msd": "PN.UTR.SIN.DEF.SUB",
"pos": "PN"
},
{
"word": "\u00e5terintr\u00e4der",
"deprel": "ET",
"dephead": "15",
"ref": "17",
"lemma": "|\u00e5terintr\u00e4da|",
"msd": "VB.PRS.AKT",
"pos": "VB"
},
{
"word": "i",
"deprel": "RA",
"dephead": "17",
"ref": "18",
"lemma": "|i|",
"msd": "PP",
"pos": "PP"
},
{
"word": "Labour",
"deprel": "PA",
"dephead": "18",
"ref": "19",
"lemma": "|",
"msd": "PM.NOM",
"pos": "PM"
},
{
"word": "och",
"deprel": "ROOT",
"dephead": null,
"ref": "20",
"lemma": "|och|",
"msd": "KN",
"pos": "KN"
},
{
"word": "det",
"deprel": "FS",
"dephead": "22",
"ref": "21",
"lemma": "|den|",
"msd": "PN.NEU.SIN.DEF.SUB+OBJ",
"pos": "PN"
},
{
"word": "kommer",
"deprel": "MS",
"dephead": "20",
"ref": "22",
"lemma": "|komma|",
"msd": "VB.PRS.AKT",
"pos": "VB"
},
{
"word": "att",
"deprel": "VG",
"dephead": "22",
"ref": "23",
"lemma": "|att|",
"msd": "IE",
"pos": "IE"
},
{
"word": "ske",
"deprel": "IF",
"dephead": "23",
"ref": "24",
"lemma": "|ske|",
"msd": "VB.INF.AKT",
"pos": "VB"
},
{
"word": "i",
"deprel": "TA",
"dephead": "24",
"ref": "25",
"lemma": "|i|i_morgon|",
"msd": "PP",
"pos": "PP"
},
{
"word": "morgon",
"deprel": "HD",
"dephead": "25",
"ref": "26",
"lemma": "|morgon|i_morgon:25|",
"msd": "NN.UTR.SIN.IND.NOM",
"pos": "NN"
},
{
"word": ".",
"deprel": "IP",
"dephead": "6",
"ref": "27",
"lemma": "|",
"msd": "MAD",
"pos": "MAD"
},
{
"word": "\u201d",
"deprel": "MS",
"dephead": "6",
"ref": "28",
"lemma": "|",
"msd": "PAD",
"pos": "PAD"
}
]
},
{
"corpus": "DA",
"match": {
"position": 442117,
"start": 21,
"end": 24
},
"structs": {
"text_date": "2010-05-19 12:41:52",
"text_id": "reportage-mp-har-gjort-ett-val-samarbetet-ar-logiskt",
"text_author": "H\u00e5kan A Bengtsson"
},
"tokens": [
{
"word": "Som",
"deprel": "AA",
"dephead": "6",
"ref": "1",
"lemma": "|",
"msd": "KN",
"pos": "KN"
},
{
"word": "en",
"deprel": "DT",
"dephead": "5",
"ref": "2",
"lemma": "|en|",
"msd": "DT.UTR.SIN.IND",
"pos": "DT"
},
{
"word": "besviken",
"deprel": "AT",
"dephead": "5",
"ref": "3",
"lemma": "|besviken|",
"msd": "JJ.POS.UTR.SIN.IND.NOM",
"pos": "JJ"
},
{
"word": "liberaldemokratisk",
"deprel": "AT",
"dephead": "5",
"ref": "4",
"lemma": "|liberaldemokratisk|",
"msd": "JJ.POS.UTR.SIN.IND.NOM",
"pos": "JJ"
},
{
"word": "bloggare",
"deprel": "UA",
"dephead": "1",
"ref": "5",
"lemma": "|bloggare|",
"msd": "NN.UTR.SIN.IND.NOM",
"pos": "NN"
},
{
"word": "uttryckte",
"deprel": "MS",
"dephead": "20",
"ref": "6",
"lemma": "|uttrycka|",
"msd": "VB.PRT.AKT",
"pos": "VB"
},
{
"word": "det",
"deprel": "SS",
"dephead": "6",
"ref": "7",
"lemma": "|den|",
"msd": "PN.NEU.SIN.DEF.SUB+OBJ",
"pos": "PN"
},
{
"word": ":",
"deprel": "IQ",
"dephead": "6",
"ref": "8",
"lemma": "|",
"msd": "MID",
"pos": "MID"
},
{
"word": "\u201c",
"deprel": "SS",
"dephead": "11",
"ref": "9",
"lemma": "|",
"msd": "NN.UTR.SIN.IND.NOM",
"pos": "NN"
},
{
"word": "Jag",
"deprel": "SS",
"dephead": "11",
"ref": "10",
"lemma": "|jag|",
"msd": "PN.UTR.SIN.DEF.SUB",
"pos": "PN"
},
{
"word": "kommer",
"deprel": "MS",
"dephead": "20",
"ref": "11",
"lemma": "|komma|",
"msd": "VB.PRS.AKT",
"pos": "VB"
},
{
"word": "fullst\u00e4ndigt",
"deprel": "AA",
"dephead": "11",
"ref": "12",
"lemma": "|fullst\u00e4ndig|",
"msd": "AB.POS",
"pos": "AB"
},
{
"word": "hata",
"deprel": "VG",
"dephead": "11",
"ref": "13",
"lemma": "|hata|",
"msd": "VB.INF.AKT",
"pos": "VB"
},
{
"word": "den",
"deprel": "DT",
"dephead": "15",
"ref": "14",
"lemma": "|den|en|",
"msd": "DT.UTR.SIN.DEF",
"pos": "DT"
},
{
"word": "dag",
"deprel": "OO",
"dephead": "13",
"ref": "15",
"lemma": "|dag|",
"msd": "NN.UTR.SIN.IND.NOM",
"pos": "NN"
},
{
"word": "jag",
"deprel": "SS",
"dephead": "17",
"ref": "16",
"lemma": "|jag|",
"msd": "PN.UTR.SIN.DEF.SUB",
"pos": "PN"
},
{
"word": "\u00e5terintr\u00e4der",
"deprel": "ET",
"dephead": "15",
"ref": "17",
"lemma": "|\u00e5terintr\u00e4da|",
"msd": "VB.PRS.AKT",
"pos": "VB"
},
{
"word": "i",
"deprel": "RA",
"dephead": "17",
"ref": "18",
"lemma": "|i|",
"msd": "PP",
"pos": "PP"
},
{
"word": "Labour",
"deprel": "PA",
"dephead": "18",
"ref": "19",
"lemma": "|",
"msd": "PM.NOM",
"pos": "PM"
},
{
"word": "och",
"deprel": "ROOT",
"dephead": null,
"ref": "20",
"lemma": "|och|",
"msd": "KN",
"pos": "KN"
},
{
"word": "det",
"deprel": "FS",
"dephead": "22",
"ref": "21",
"lemma": "|den|",
"msd": "PN.NEU.SIN.DEF.SUB+OBJ",
"pos": "PN"
},
{
"word": "kommer",
"deprel": "MS",
"dephead": "20",
"ref": "22",
"lemma": "|komma|",
"msd": "VB.PRS.AKT",
"pos": "VB"
},
{
"word": "att",
"deprel": "VG",
"dephead": "22",
"ref": "23",
"lemma": "|att|",
"msd": "IE",
"pos": "IE"
},
{
"word": "ske",
"deprel": "IF",
"dephead": "23",
"ref": "24",
"lemma": "|ske|",
"msd": "VB.INF.AKT",
"pos": "VB"
},
{
"word": "i",
"deprel": "TA",
"dephead": "24",
"ref": "25",
"lemma": "|i|i_morgon|",
"msd": "PP",
"pos": "PP"
},
{
"word": "morgon",
"deprel": "HD",
"dephead": "25",
"ref": "26",
"lemma": "|morgon|i_morgon:25|",
"msd": "NN.UTR.SIN.IND.NOM",
"pos": "NN"
},
{
"word": ".",
"deprel": "IP",
"dephead": "6",
"ref": "27",
"lemma": "|",
"msd": "MAD",
"pos": "MAD"
},
{
"word": "\u201d",
"deprel": "MS",
"dephead": "6",
"ref": "28",
"lemma": "|",
"msd": "PAD",
"pos": "PAD"
}
]
},
{
"corpus": "DA",
"match": {
"position": 453098,
"start": 1,
"end": 6
},
"structs": {
"text_date": "2010-05-21 11:58:49",
"text_id": "6890",
"text_author": "Yonna Waltersson"
},
"tokens": [
{
"word": "Bonusen",
"deprel": "SS",
"dephead": "2",
"ref": "1",
"lemma": "|bonus|",
"msd": "NN.UTR.SIN.DEF.NOM",
"pos": "NN"
},
{
"word": "kommer",
"deprel": "ROOT",
"dephead": null,
"ref": "2",
"lemma": "|komma|komma_sig|",
"msd": "VB.PRS.AKT",
"pos": "VB"
},
{
"word": "i",
"deprel": "+A",
"dephead": "2",
"ref": "3",
"lemma": "|i|",
"msd": "PP",
"pos": "PP"
},
{
"word": "sig",
"deprel": "PA",
"dephead": "3",
"ref": "4",
"lemma": "|sig|komma_sig:2|",
"msd": "PN.UTR+NEU.SIN+PLU.DEF.OBJ",
"pos": "PN"
},
{
"word": "inte",
"deprel": "NA",
"dephead": "2",
"ref": "5",
"lemma": "|inte|",
"msd": "AB",
"pos": "AB"
},
{
"word": "f\u00f6rb\u00e4ttra",
"deprel": "VG",
"dephead": "2",
"ref": "6",
"lemma": "|f\u00f6rb\u00e4ttra|",
"msd": "VB.INF.AKT",
"pos": "VB"
},
{
"word": "m\u00f6jligheten",
"deprel": "OO",
"dephead": "6",
"ref": "7",
"lemma": "|m\u00f6jlighet|",
"msd": "NN.UTR.SIN.DEF.NOM",
"pos": "NN"
},
{
"word": "att",
"deprel": "ET",
"dephead": "7",
"ref": "8",
"lemma": "|att|",
"msd": "IE",
"pos": "IE"
},
{
"word": "l\u00e4ra",
"deprel": "IF",
"dephead": "8",
"ref": "9",
"lemma": "|l\u00e4ra|l\u00e4ra_sig|",
"msd": "VB.INF.AKT",
"pos": "VB"
},
{
"word": "sig",
"deprel": "IO",
"dephead": "9",
"ref": "10",
"lemma": "|sig|l\u00e4ra_sig:9|",
"msd": "PN.UTR+NEU.SIN+PLU.DEF.OBJ",
"pos": "PN"
},
{
"word": "ett",
"deprel": "DT",
"dephead": "12",
"ref": "11",
"lemma": "|en|",
"msd": "DT.NEU.SIN.IND",
"pos": "DT"
},
{
"word": "spr\u00e5k",
"deprel": "OO",
"dephead": "9",
"ref": "12",
"lemma": "|spr\u00e5k|",
"msd": "NN.NEU.SIN.IND.NOM",
"pos": "NN"
},
{
"word": ",",
"deprel": "IK",
"dephead": "6",
"ref": "13",
"lemma": "|",
"msd": "MID",
"pos": "MID"
},
{
"word": "vad",
"deprel": "SS",
"dephead": "16",
"ref": "14",
"lemma": "|vad|",
"msd": "HP.NEU.SIN.IND",
"pos": "HP"
},
{
"word": "som",
"deprel": "XX",
"dephead": "16",
"ref": "15",
"lemma": "|",
"msd": "HP.-.-.-",
"pos": "HP"
},
{
"word": "beh\u00f6vs",
"deprel": "SS",
"dephead": "17",
"ref": "16",
"lemma": "|beh\u00f6va|beh\u00f6vas|",
"msd": "VB.PRS.SFO",
"pos": "VB"
},
{
"word": "\u00e4r",
"deprel": "MS",
"dephead": "2",
"ref": "17",
"lemma": "|vara|",
"msd": "VB.PRS.AKT",
"pos": "VB"
},
{
"word": "en",
"deprel": "DT",
"dephead": "20",
"ref": "18",
"lemma": "|en|",
"msd": "DT.UTR.SIN.IND",
"pos": "DT"
},
{
"word": "f\u00f6rb\u00e4ttrad",
"deprel": "AT",
"dephead": "20",
"ref": "19",
"lemma": "|f\u00f6rb\u00e4ttra|",
"msd": "PC.PRF.UTR.SIN.IND.NOM",
"pos": "PC"
},
{
"word": "kvalitet",
"deprel": "SP",
"dephead": "17",
"ref": "20",
"lemma": "|kvalitet|",
"msd": "NN.UTR.SIN.IND.NOM",
"pos": "NN"
},
{
"word": "p\u00e5",
"deprel": "RA",
"dephead": "17",
"ref": "21",
"lemma": "|p\u00e5|",
"msd": "PP",
"pos": "PP"
},
{
"word": "sj\u00e4lva",
"deprel": "DT",
"dephead": "23",
"ref": "22",
"lemma": "|sj\u00e4lv|sj\u00e4lva|",
"msd": "JJ.POS.UTR+NEU.SIN.DEF.NOM",
"pos": "JJ"
},
{
"word": "utbildningen",
"deprel": "PA",
"dephead": "21",
"ref": "23",
"lemma": "|utbildning|",
"msd": "NN.UTR.SIN.DEF.NOM",
"pos": "NN"
},
{
"word": ".",
"deprel": "IP",
"dephead": "2",
"ref": "24",
"lemma": "|",
"msd": "MAD",
"pos": "MAD"
}
]
}
],
"hits": 31,
"corpus_hits": {
"DA": 31
},
"corpus_order": [
"DA"
],
"query_data": "eJwNwssNgEAIBcCWYOUjejKxER6w_Zegk7ESrYwybp21_RRIof8RC6TSTZiRnZq8HBxETmNM3snQ-32ugz_PBROK\n",
"time": 1.8477859497070312
}
